[
    {
        "ID": "Kihm-487953",
        "bookID": "165",
        "categories": [
            "cop"
        ],
        "clength": 21,
        "html": "<div class=\"imtblocks\">\n\t<div class=\"imtblock\">\n\t\t<div class=\"srcblock\">Rèv</div>\n\t\t<div class=\"glossblock\">dream</div>\n\t</div>\n\t<div class=\"imtblock\">\n\t\t<div class=\"srcblock\">lòm</div>\n\t\t<div class=\"glossblock\">man</div>\n\t</div>\n\t<div class=\"imtblock\">\n\t\t<div class=\"srcblock\">se</div>\n\t\t<div class=\"glossblock\"><span class=\"sc\">cop</span></div>\n\t</div>\n\t<div class=\"imtblock\">\n\t\t<div class=\"srcblock\">limit</div>\n\t\t<div class=\"glossblock\">limit</div>\n\t</div>\n\t<div class=\"imtblock\">\n\t\t<div class=\"srcblock\">lòm.</div>\n\t\t<div class=\"glossblock\">man</div>\n\t</div>\n</div>\n",
        "imt": "dream man \\textsc{cop} limit man",
        "imtwordsbare": [
            "dream",
            "man",
            "COP",
            "limit",
            "man"
        ],
        "imtwordstex": [
            "dream",
            "man",
            "\\textsc{cop}",
            "limit",
            "man"
        ],
        "language": "und",
        "src": "Rèv lòm se limit lòm.",
        "srcwordsbare": [
            "Rèv",
            "lòm",
            "se",
            "limit",
            "lòm."
        ],
        "srcwordstex": [
            "Rèv",
            "lòm",
            "se",
            "limit",
            "lòm."
        ],
        "trs": "\\trad{Man's dream is man's limit.} (\\emph{Le rêve de l'homme est la limite de l'homme})\\\\",
        "wlength": 5
    },
    {
        "ID": "Kihm-462779",
        "bookID": "165",
        "categories": [
            "cop"
        ],
        "clength": 19,
        "html": "<div class=\"imtblocks\">\n\t<div class=\"imtblock\">\n\t\t<div class=\"srcblock\">Se</div>\n\t\t<div class=\"glossblock\"><span class=\"sc\">cop</span></div>\n\t</div>\n\t<div class=\"imtblock\">\n\t\t<div class=\"srcblock\">damou</div>\n\t\t<div class=\"glossblock\">in.love</div>\n\t</div>\n\t<div class=\"imtblock\">\n\t\t<div class=\"srcblock\">Jan</div>\n\t\t<div class=\"glossblock\">John</div>\n\t</div>\n\t<div class=\"imtblock\">\n\t\t<div class=\"srcblock\">damou.</div>\n\t\t<div class=\"glossblock\">in.love</div>\n\t</div>\n</div>\n",
        "imt": "\\textsc{cop} in.love John in.love",
        "imtwordsbare": [
            "COP",
            "in.love",
            "John",
            "in.love"
        ],
        "imtwordstex": [
            "\\textsc{cop}",
            "in.love",
            "John",
            "in.love"
        ],
        "language": "und",
        "src": "Se damou Jan damou.",
        "srcwordsbare": [
            "Se",
            "damou",
            "Jan",
            "damou."
        ],
        "srcwordstex": [
            "Se",
            "damou",
            "Jan",
            "damou."
        ],
        "trs": "\\trad{John \\textsc{is} in love.} \\\\",
        "wlength": 4
    },
    {
        "ID": "Kihm-438837",
        "bookID": "165",
        "categories": [
            "3sg",
            "cop"
        ],
        "clength": 17,
        "html": "<div class=\"imtblocks\">\n\t<div class=\"imtblock\">\n\t\t<div class=\"srcblock\">Se</div>\n\t\t<div class=\"glossblock\"><span class=\"sc\">cop</span></div>\n\t</div>\n\t<div class=\"imtblock\">\n\t\t<div class=\"srcblock\">grangou</div>\n\t\t<div class=\"glossblock\">unscrupulous</div>\n\t</div>\n\t<div class=\"imtblock\">\n\t\t<div class=\"srcblock\">li</div>\n\t\t<div class=\"glossblock\"><span class=\"sc\">3sg</span></div>\n\t</div>\n\t<div class=\"imtblock\">\n\t\t<div class=\"srcblock\">ye.</div>\n\t\t<div class=\"glossblock\"><span class=\"sc\">cop</span></div>\n\t</div>\n</div>\n",
        "imt": "\\textsc{cop} unscrupulous \\textsc{3sg} \\textsc{cop}",
        "imtwordsbare": [
            "COP",
            "unscrupulous",
            "3SG",
            "COP"
        ],
        "imtwordstex": [
            "\\textsc{cop}",
            "unscrupulous",
            "\\textsc{3sg}",
            "\\textsc{cop}"
        ],
        "language": "und",
        "src": "Se grangou li ye.",
        "srcwordsbare": [
            "Se",
            "grangou",
            "li",
            "ye."
        ],
        "srcwordstex": [
            "Se",
            "grangou",
            "li",
            "ye."
        ],
        "trs": "\\trad{S/he \\textsc{is} unscrupulous.} \\\\",
        "wlength": 4
    },
    {
        "ID": "Kihm--62175",
        "bookID": "165",
        "categories": [
            "2sg",
            "cop"
        ],
        "clength": 18,
        "html": "<div class=\"imtblocks\">\n\t<div class=\"imtblock\">\n\t\t<div class=\"srcblock\">Tout</div>\n\t\t<div class=\"glossblock\">all</div>\n\t</div>\n\t<div class=\"imtblock\">\n\t\t<div class=\"srcblock\">sa</div>\n\t\t<div class=\"glossblock\">this</div>\n\t</div>\n\t<div class=\"imtblock\">\n\t\t<div class=\"srcblock\">se</div>\n\t\t<div class=\"glossblock\"><span class=\"sc\">cop</span></div>\n\t</div>\n\t<div class=\"imtblock\">\n\t\t<div class=\"srcblock\">pou</div>\n\t\t<div class=\"glossblock\">for</div>\n\t</div>\n\t<div class=\"imtblock\">\n\t\t<div class=\"srcblock\">ou.</div>\n\t\t<div class=\"glossblock\"><span class=\"sc\">2sg</span></div>\n\t</div>\n</div>\n",
        "imt": "all this \\textsc{cop} for \\textsc{2sg}",
        "imtwordsbare": [
            "all",
            "this",
            "COP",
            "for",
            "2SG"
        ],
        "imtwordstex": [
            "all",
            "this",
            "\\textsc{cop}",
            "for",
            "\\textsc{2sg}"
        ],
        "language": "und",
        "src": "Tout sa se pou ou.",
        "srcwordsbare": [
            "Tout",
            "sa",
            "se",
            "pou",
            "ou."
        ],
        "srcwordstex": [
            "Tout",
            "sa",
            "se",
            "pou",
            "ou."
        ],
        "trs": "\\trad{All this is for you.} \\\\",
        "wlength": 5
    },
    {
        "ID": "Kihm-171784",
        "bookID": "165",
        "categories": [
            "1sg",
            "2sg",
            "cop",
            "neg",
            "pst"
        ],
        "clength": 40,
        "html": "<div class=\"imtblocks\">\n\t<div class=\"imtblock\">\n\t\t<div class=\"srcblock\">M</div>\n\t\t<div class=\"glossblock\"><span class=\"sc\">1sg</span></div>\n\t</div>\n\t<div class=\"imtblock\">\n\t\t<div class=\"srcblock\">pa</div>\n\t\t<div class=\"glossblock\"><span class=\"sc\">neg</span></div>\n\t</div>\n\t<div class=\"imtblock\">\n\t\t<div class=\"srcblock\">te</div>\n\t\t<div class=\"glossblock\"><span class=\"sc\">pst</span></div>\n\t</div>\n\t<div class=\"imtblock\">\n\t\t<div class=\"srcblock\">di</div>\n\t\t<div class=\"glossblock\">tell</div>\n\t</div>\n\t<div class=\"imtblock\">\n\t\t<div class=\"srcblock\">ou</div>\n\t\t<div class=\"glossblock\"><span class=\"sc\">2sg</span></div>\n\t</div>\n\t<div class=\"imtblock\">\n\t\t<div class=\"srcblock\">vi</div>\n\t\t<div class=\"glossblock\">life</div>\n\t</div>\n\t<div class=\"imtblock\">\n\t\t<div class=\"srcblock\">mwen</div>\n\t\t<div class=\"glossblock\"><span class=\"sc\">1sg</span></div>\n\t</div>\n\t<div class=\"imtblock\">\n\t\t<div class=\"srcblock\">se</div>\n\t\t<div class=\"glossblock\"><span class=\"sc\">cop</span></div>\n\t</div>\n\t<div class=\"imtblock\">\n\t\t<div class=\"srcblock\">nan</div>\n\t\t<div class=\"glossblock\">in</div>\n\t</div>\n\t<div class=\"imtblock\">\n\t\t<div class=\"srcblock\">navigasyon.</div>\n\t\t<div class=\"glossblock\">navigation</div>\n\t</div>\n</div>\n",
        "imt": "\\textsc{1sg} \\textsc{neg} \\textsc{pst} tell \\textsc{2sg} life \\textsc{1sg} \\textsc{cop} in navigation",
        "imtwordsbare": [
            "1SG",
            "NEG",
            "PST",
            "tell",
            "2SG",
            "life",
            "1SG",
            "COP",
            "in",
            "navigation"
        ],
        "imtwordstex": [
            "\\textsc{1sg}",
            "\\textsc{neg}",
            "\\textsc{pst}",
            "tell",
            "\\textsc{2sg}",
            "life",
            "\\textsc{1sg}",
            "\\textsc{cop}",
            "in",
            "navigation"
        ],
        "language": "und",
        "polarity": "negative",
        "src": "M pa te di ou vi mwen se nan navigasyon.",
        "srcwordsbare": [
            "M",
            "pa",
            "te",
            "di",
            "ou",
            "vi",
            "mwen",
            "se",
            "nan",
            "navigasyon."
        ],
        "srcwordstex": [
            "M",
            "pa",
            "te",
            "di",
            "ou",
            "vi",
            "mwen",
            "se",
            "nan",
            "navigasyon."
        ],
        "trs": "\\trad{I did not tell you my life is in navigation.} \\\\",
        "wlength": 10
    },
    {
        "ID": "Kihm--84951",
        "bookID": "165",
        "categories": [
            "3sg",
            "pst"
        ],
        "clength": 21,
        "html": "<div class=\"imtblocks\">\n\t<div class=\"imtblock\">\n\t\t<div class=\"srcblock\">Li</div>\n\t\t<div class=\"glossblock\"><span class=\"sc\">3sg</span></div>\n\t</div>\n\t<div class=\"imtblock\">\n\t\t<div class=\"srcblock\">te</div>\n\t\t<div class=\"glossblock\"><span class=\"sc\">pst</span></div>\n\t</div>\n\t<div class=\"imtblock\">\n\t\t<div class=\"srcblock\">gen</div>\n\t\t<div class=\"glossblock\">have</div>\n\t</div>\n\t<div class=\"imtblock\">\n\t\t<div class=\"srcblock\">twa</div>\n\t\t<div class=\"glossblock\">three</div>\n\t</div>\n\t<div class=\"imtblock\">\n\t\t<div class=\"srcblock\">zoranj.</div>\n\t\t<div class=\"glossblock\">orange</div>\n\t</div>\n</div>\n",
        "imt": "\\textsc{3sg} \\textsc{pst} have three orange",
        "imtwordsbare": [
            "3SG",
            "PST",
            "have",
            "three",
            "orange"
        ],
        "imtwordstex": [
            "\\textsc{3sg}",
            "\\textsc{pst}",
            "have",
            "three",
            "orange"
        ],
        "language": "und",
        "src": "Li te gen twa zoranj.",
        "srcwordsbare": [
            "Li",
            "te",
            "gen",
            "twa",
            "zoranj."
        ],
        "srcwordstex": [
            "Li",
            "te",
            "gen",
            "twa",
            "zoranj."
        ],
        "trs": "\\trad{S/he had three oranges.} \\\\",
        "wlength": 5
    },
    {
        "ID": "Kihm--43943",
        "bookID": "165",
        "categories": [
            "3sg",
            "prog",
            "pst"
        ],
        "clength": 25,
        "html": "<div class=\"imtblocks\">\n\t<div class=\"imtblock\">\n\t\t<div class=\"srcblock\">Li</div>\n\t\t<div class=\"glossblock\"><span class=\"sc\">3sg</span></div>\n\t</div>\n\t<div class=\"imtblock\">\n\t\t<div class=\"srcblock\">t(e)</div>\n\t\t<div class=\"glossblock\"><span class=\"sc\">pst</span></div>\n\t</div>\n\t<div class=\"imtblock\">\n\t\t<div class=\"srcblock\">ap</div>\n\t\t<div class=\"glossblock\"><span class=\"sc\">prog</span></div>\n\t</div>\n\t<div class=\"imtblock\">\n\t\t<div class=\"srcblock\">boukanen</div>\n\t\t<div class=\"glossblock\">roast</div>\n\t</div>\n\t<div class=\"imtblock\">\n\t\t<div class=\"srcblock\">mayi.</div>\n\t\t<div class=\"glossblock\">maize</div>\n\t</div>\n</div>\n",
        "imt": "\\textsc{3sg} \\textsc{pst} \\textsc{prog} roast maize",
        "imtwordsbare": [
            "3SG",
            "PST",
            "PROG",
            "roast",
            "maize"
        ],
        "imtwordstex": [
            "\\textsc{3sg}",
            "\\textsc{pst}",
            "\\textsc{prog}",
            "roast",
            "maize"
        ],
        "language": "und",
        "src": "Li t(e) ap boukanen mayi.",
        "srcwordsbare": [
            "Li",
            "t(e)",
            "ap",
            "boukanen",
            "mayi."
        ],
        "srcwordstex": [
            "Li",
            "t(e)",
            "ap",
            "boukanen",
            "mayi."
        ],
        "trs": "\\trad{S/he was roasting maize.} \\\\",
        "wlength": 5
    },
    {
        "ID": "Kihm--49606",
        "bookID": "165",
        "categories": [
            "1sg",
            "cop",
            "pst"
        ],
        "clength": 22,
        "html": "<div class=\"imtblocks\">\n\t<div class=\"imtblock\">\n\t\t<div class=\"srcblock\">Di</div>\n\t\t<div class=\"glossblock\">tell</div>\n\t</div>\n\t<div class=\"imtblock\">\n\t\t<div class=\"srcblock\">m</div>\n\t\t<div class=\"glossblock\"><span class=\"sc\">1sg</span></div>\n\t</div>\n\t<div class=\"imtblock\">\n\t\t<div class=\"srcblock\">kijan</div>\n\t\t<div class=\"glossblock\">how</div>\n\t</div>\n\t<div class=\"imtblock\">\n\t\t<div class=\"srcblock\">lavi</div>\n\t\t<div class=\"glossblock\">life</div>\n\t</div>\n\t<div class=\"imtblock\">\n\t\t<div class=\"srcblock\">te</div>\n\t\t<div class=\"glossblock\"><span class=\"sc\">pst</span></div>\n\t</div>\n\t<div class=\"imtblock\">\n\t\t<div class=\"srcblock\">ye.</div>\n\t\t<div class=\"glossblock\"><span class=\"sc\">cop</span></div>\n\t</div>\n</div>\n",
        "imt": "tell \\textsc{1sg} how life \\textsc{pst} \\textsc{cop}",
        "imtwordsbare": [
            "tell",
            "1SG",
            "how",
            "life",
            "PST",
            "COP"
        ],
        "imtwordstex": [
            "tell",
            "\\textsc{1sg}",
            "how",
            "life",
            "\\textsc{pst}",
            "\\textsc{cop}"
        ],
        "language": "und",
        "src": "Di m kijan lavi te ye.",
        "srcwordsbare": [
            "Di",
            "m",
            "kijan",
            "lavi",
            "te",
            "ye."
        ],
        "srcwordstex": [
            "Di",
            "m",
            "kijan",
            "lavi",
            "te",
            "ye."
        ],
        "trs": "\\trad{tell me how life was.} (\\emph{dis-moi comment était la vie.}) \\\\",
        "wlength": 6
    },
    {
        "ID": "Kihm--41130",
        "bookID": "165",
        "categories": [
            "3sg",
            "cop",
            "def",
            "rel"
        ],
        "clength": 34,
        "html": "<div class=\"imtblocks\">\n\t<div class=\"imtblock\">\n\t\t<div class=\"srcblock\">Sa</div>\n\t\t<div class=\"glossblock\">what</div>\n\t</div>\n\t<div class=\"imtblock\">\n\t\t<div class=\"srcblock\">l'</div>\n\t\t<div class=\"glossblock\"><span class=\"sc\">3sg</span></div>\n\t</div>\n\t<div class=\"imtblock\">\n\t\t<div class=\"srcblock\">ye</div>\n\t\t<div class=\"glossblock\"><span class=\"sc\">cop</span></div>\n\t</div>\n\t<div class=\"imtblock\">\n\t\t<div class=\"srcblock\">nèg</div>\n\t\t<div class=\"glossblock\">man</div>\n\t</div>\n\t<div class=\"imtblock\">\n\t\t<div class=\"srcblock\">la</div>\n\t\t<div class=\"glossblock\"><span class=\"sc\">def</span></div>\n\t</div>\n\t<div class=\"imtblock\">\n\t\t<div class=\"srcblock\">ki</div>\n\t\t<div class=\"glossblock\"><span class=\"sc\">rel</span></div>\n\t</div>\n\t<div class=\"imtblock\">\n\t\t<div class=\"srcblock\">marye</div>\n\t\t<div class=\"glossblock\">marry</div>\n\t</div>\n\t<div class=\"imtblock\">\n\t\t<div class=\"srcblock\">avè</div>\n\t\t<div class=\"glossblock\">with</div>\n\t</div>\n\t<div class=\"imtblock\">\n\t\t<div class=\"srcblock\">fi</div>\n\t\t<div class=\"glossblock\">girl</div>\n\t</div>\n\t<div class=\"imtblock\">\n\t\t<div class=\"srcblock\">a?</div>\n\t\t<div class=\"glossblock\"><span class=\"sc\">def</span></div>\n\t</div>\n</div>\n",
        "imt": "what \\textsc{3sg} \\textsc{cop} man \\textsc{def} \\textsc{rel} marry with girl \\textsc{def}",
        "imtwordsbare": [
            "what",
            "3SG",
            "COP",
            "man",
            "DEF",
            "REL",
            "marry",
            "with",
            "girl",
            "DEF"
        ],
        "imtwordstex": [
            "what",
            "\\textsc{3sg}",
            "\\textsc{cop}",
            "man",
            "\\textsc{def}",
            "\\textsc{rel}",
            "marry",
            "with",
            "girl",
            "\\textsc{def}"
        ],
        "language": "und",
        "src": "Sa l' ye nèg la ki marye avè fi a?",
        "srcwordsbare": [
            "Sa",
            "l'",
            "ye",
            "nèg",
            "la",
            "ki",
            "marye",
            "avè",
            "fi",
            "a?"
        ],
        "srcwordstex": [
            "Sa",
            "l'",
            "ye",
            "nèg",
            "la",
            "ki",
            "marye",
            "avè",
            "fi",
            "a?"
        ],
        "trs": "\\trad{What is he, the man who married the girl?} \\\\",
        "wlength": 10
    },
    {
        "ID": "Kihm--58752",
        "bookID": "165",
        "categories": [
            "1sg",
            "cop",
            "def",
            "dem",
            "pst"
        ],
        "clength": 36,
        "html": "<div class=\"imtblocks\">\n\t<div class=\"imtblock\">\n\t\t<div class=\"srcblock\">Nonm</div>\n\t\t<div class=\"glossblock\">man</div>\n\t</div>\n\t<div class=\"imtblock\">\n\t\t<div class=\"srcblock\">nan</div>\n\t\t<div class=\"glossblock\"><span class=\"sc\">def</span></div>\n\t</div>\n\t<div class=\"imtblock\">\n\t\t<div class=\"srcblock\">te</div>\n\t\t<div class=\"glossblock\"><span class=\"sc\">pst</span></div>\n\t</div>\n\t<div class=\"imtblock\">\n\t\t<div class=\"srcblock\">pi</div>\n\t\t<div class=\"glossblock\">more</div>\n\t</div>\n\t<div class=\"imtblock\">\n\t\t<div class=\"srcblock\">gran</div>\n\t\t<div class=\"glossblock\">big</div>\n\t</div>\n\t<div class=\"imtblock\">\n\t\t<div class=\"srcblock\">m</div>\n\t\t<div class=\"glossblock\"><span class=\"sc\">1sg</span></div>\n\t</div>\n\t<div class=\"imtblock\">\n\t\t<div class=\"srcblock\">te</div>\n\t\t<div class=\"glossblock\"><span class=\"sc\">pst</span></div>\n\t</div>\n\t<div class=\"imtblock\">\n\t\t<div class=\"srcblock\">ye</div>\n\t\t<div class=\"glossblock\"><span class=\"sc\">cop</span></div>\n\t</div>\n\t<div class=\"imtblock\">\n\t\t<div class=\"srcblock\">lè</div>\n\t\t<div class=\"glossblock\">time</div>\n\t</div>\n\t<div class=\"imtblock\">\n\t\t<div class=\"srcblock\">sa</div>\n\t\t<div class=\"glossblock\"><span class=\"sc\">dem</span></div>\n\t</div>\n\t<div class=\"imtblock\">\n\t\t<div class=\"srcblock\">a.</div>\n\t\t<div class=\"glossblock\"><span class=\"sc\">def</span></div>\n\t</div>\n</div>\n",
        "imt": "man \\textsc{def} \\textsc{pst} more big \\textsc{1sg} \\textsc{pst} \\textsc{cop} time \\textsc{dem} \\textsc{def}",
        "imtwordsbare": [
            "man",
            "DEF",
            "PST",
            "more",
            "big",
            "1SG",
            "PST",
            "COP",
            "time",
            "DEM",
            "DEF"
        ],
        "imtwordstex": [
            "man",
            "\\textsc{def}",
            "\\textsc{pst}",
            "more",
            "big",
            "\\textsc{1sg}",
            "\\textsc{pst}",
            "\\textsc{cop}",
            "time",
            "\\textsc{dem}",
            "\\textsc{def}"
        ],
        "language": "und",
        "src": "Nonm nan te pi gran m te ye lè sa a.",
        "srcwordsbare": [
            "Nonm",
            "nan",
            "te",
            "pi",
            "gran",
            "m",
            "te",
            "ye",
            "lè",
            "sa",
            "a."
        ],
        "srcwordstex": [
            "Nonm",
            "nan",
            "te",
            "pi",
            "gran",
            "m",
            "te",
            "ye",
            "lè",
            "sa",
            "a."
        ],
        "trs": "\\trad{The man was bigger than I was at that time.} \\\\",
        "wlength": 11
    },
    {
        "ID": "Kihm--75659",
        "bookID": "165",
        "categories": [
            "def"
        ],
        "clength": 24,
        "html": "<div class=\"imtblocks\">\n\t<div class=\"imtblock\">\n\t\t<div class=\"srcblock\">Rete</div>\n\t\t<div class=\"glossblock\">remain</div>\n\t</div>\n\t<div class=\"imtblock\">\n\t\t<div class=\"srcblock\">yon</div>\n\t\t<div class=\"glossblock\">one</div>\n\t</div>\n\t<div class=\"imtblock\">\n\t\t<div class=\"srcblock\">nèg</div>\n\t\t<div class=\"glossblock\">man</div>\n\t</div>\n\t<div class=\"imtblock\">\n\t\t<div class=\"srcblock\">nan</div>\n\t\t<div class=\"glossblock\">in</div>\n\t</div>\n\t<div class=\"imtblock\">\n\t\t<div class=\"srcblock\">kay</div>\n\t\t<div class=\"glossblock\">house</div>\n\t</div>\n\t<div class=\"imtblock\">\n\t\t<div class=\"srcblock\">la.</div>\n\t\t<div class=\"glossblock\"><span class=\"sc\">def</span></div>\n\t</div>\n</div>\n",
        "imt": "remain one man in house \\textsc{def}",
        "imtwordsbare": [
            "remain",
            "one",
            "man",
            "in",
            "house",
            "DEF"
        ],
        "imtwordstex": [
            "remain",
            "one",
            "man",
            "in",
            "house",
            "\\textsc{def}"
        ],
        "language": "und",
        "src": "Rete yon nèg nan kay la.",
        "srcwordsbare": [
            "Rete",
            "yon",
            "nèg",
            "nan",
            "kay",
            "la."
        ],
        "srcwordstex": [
            "Rete",
            "yon",
            "nèg",
            "nan",
            "kay",
            "la."
        ],
        "trs": "\\trad{There remains one man in the house.} \\\\",
        "wlength": 6
    },
    {
        "ID": "Kihm--82313",
        "bookID": "165",
        "categories": [],
        "clength": 23,
        "html": "<div class=\"imtblocks\">\n\t<div class=\"imtblock\">\n\t\t<div class=\"srcblock\">Sanble</div>\n\t\t<div class=\"glossblock\">seem</div>\n\t</div>\n\t<div class=\"imtblock\">\n\t\t<div class=\"srcblock\">Mari</div>\n\t\t<div class=\"glossblock\">Mary</div>\n\t</div>\n\t<div class=\"imtblock\">\n\t\t<div class=\"srcblock\">renmen</div>\n\t\t<div class=\"glossblock\">love</div>\n\t</div>\n\t<div class=\"imtblock\">\n\t\t<div class=\"srcblock\">Jan.</div>\n\t\t<div class=\"glossblock\">John</div>\n\t</div>\n</div>\n",
        "imt": "seem Mary love John",
        "imtwordsbare": [
            "seem",
            "Mary",
            "love",
            "John"
        ],
        "imtwordstex": [
            "seem",
            "Mary",
            "love",
            "John"
        ],
        "language": "und",
        "src": "Sanble Mari renmen Jan.",
        "srcwordsbare": [
            "Sanble",
            "Mari",
            "renmen",
            "Jan."
        ],
        "srcwordstex": [
            "Sanble",
            "Mari",
            "renmen",
            "Jan."
        ],
        "trs": "\\trad{It seems that Mary loves John.} \\\\",
        "wlength": 4
    },
    {
        "ID": "Kihm-335131",
        "bookID": "165",
        "categories": [
            "1sg",
            "cop"
        ],
        "clength": 31,
        "html": "<div class=\"imtblocks\">\n\t<div class=\"imtblock\">\n\t\t<div class=\"srcblock\">M</div>\n\t\t<div class=\"glossblock\"><span class=\"sc\">1sg</span></div>\n\t</div>\n\t<div class=\"imtblock\">\n\t\t<div class=\"srcblock\">se</div>\n\t\t<div class=\"glossblock\"><span class=\"sc\">cop</span></div>\n\t</div>\n\t<div class=\"imtblock\">\n\t\t<div class=\"srcblock\">espas</div>\n\t\t<div class=\"glossblock\">space</div>\n\t</div>\n\t<div class=\"imtblock\">\n\t\t<div class=\"srcblock\">nan</div>\n\t\t<div class=\"glossblock\">in</div>\n\t</div>\n\t<div class=\"imtblock\">\n\t\t<div class=\"srcblock\">mitan</div>\n\t\t<div class=\"glossblock\">middle</div>\n\t</div>\n\t<div class=\"imtblock\">\n\t\t<div class=\"srcblock\">de</div>\n\t\t<div class=\"glossblock\">two</div>\n\t</div>\n\t<div class=\"imtblock\">\n\t\t<div class=\"srcblock\">pyebwa.</div>\n\t\t<div class=\"glossblock\">tree</div>\n\t</div>\n</div>\n",
        "imt": "\\textsc{1sg} \\textsc{cop} space in middle two tree",
        "imtwordsbare": [
            "1SG",
            "COP",
            "space",
            "in",
            "middle",
            "two",
            "tree"
        ],
        "imtwordstex": [
            "\\textsc{1sg}",
            "\\textsc{cop}",
            "space",
            "in",
            "middle",
            "two",
            "tree"
        ],
        "language": "und",
        "src": "M se espas nan mitan de pyebwa.",
        "srcwordsbare": [
            "M",
            "se",
            "espas",
            "nan",
            "mitan",
            "de",
            "pyebwa."
        ],
        "srcwordstex": [
            "M",
            "se",
            "espas",
            "nan",
            "mitan",
            "de",
            "pyebwa."
        ],
        "trs": "\\trad{I am the space between two trees.} (\\emph{je suis l'espace entre deux arbres}) \\\\",
        "wlength": 7
    },
    {
        "ID": "Kihm-394335",
        "bookID": "165",
        "categories": [
            "2sg",
            "cop",
            "neg",
            "pst"
        ],
        "clength": 20,
        "html": "<div class=\"imtblocks\">\n\t<div class=\"imtblock\">\n\t\t<div class=\"srcblock\">Jan</div>\n\t\t<div class=\"glossblock\">John</div>\n\t</div>\n\t<div class=\"imtblock\">\n\t\t<div class=\"srcblock\">se</div>\n\t\t<div class=\"glossblock\"><span class=\"sc\">cop</span></div>\n\t</div>\n\t<div class=\"imtblock\">\n\t\t<div class=\"srcblock\">pa</div>\n\t\t<div class=\"glossblock\"><span class=\"sc\">neg</span></div>\n\t</div>\n\t<div class=\"imtblock\">\n\t\t<div class=\"srcblock\">te</div>\n\t\t<div class=\"glossblock\"><span class=\"sc\">pst</span></div>\n\t</div>\n\t<div class=\"imtblock\">\n\t\t<div class=\"srcblock\">papa</div>\n\t\t<div class=\"glossblock\">father</div>\n\t</div>\n\t<div class=\"imtblock\">\n\t\t<div class=\"srcblock\">w.</div>\n\t\t<div class=\"glossblock\"><span class=\"sc\">2sg</span></div>\n\t</div>\n</div>\n",
        "imt": "John \\textsc{cop} \\textsc{neg} \\textsc{pst} father \\textsc{2sg}",
        "imtwordsbare": [
            "John",
            "COP",
            "NEG",
            "PST",
            "father",
            "2SG"
        ],
        "imtwordstex": [
            "John",
            "\\textsc{cop}",
            "\\textsc{neg}",
            "\\textsc{pst}",
            "father",
            "\\textsc{2sg}"
        ],
        "language": "und",
        "src": "Jan se pa te papa w.",
        "srcwordsbare": [
            "Jan",
            "se",
            "pa",
            "te",
            "papa",
            "w."
        ],
        "srcwordstex": [
            "Jan",
            "se",
            "pa",
            "te",
            "papa",
            "w."
        ],
        "trs": "\\trad{John wasn't your father.} \\\\",
        "wlength": 6
    },
    {
        "ID": "Kihm--32899",
        "bookID": "165",
        "categories": [
            "cop",
            "fut",
            "indf"
        ],
        "clength": 24,
        "html": "<div class=\"imtblocks\">\n\t<div class=\"imtblock\">\n\t\t<div class=\"srcblock\">Sa</div>\n\t\t<div class=\"glossblock\">that</div>\n\t</div>\n\t<div class=\"imtblock\">\n\t\t<div class=\"srcblock\">se</div>\n\t\t<div class=\"glossblock\"><span class=\"sc\">cop</span></div>\n\t</div>\n\t<div class=\"imtblock\">\n\t\t<div class=\"srcblock\">va</div>\n\t\t<div class=\"glossblock\"><span class=\"sc\">fut</span></div>\n\t</div>\n\t<div class=\"imtblock\">\n\t\t<div class=\"srcblock\">yon</div>\n\t\t<div class=\"glossblock\"><span class=\"sc\">indf</span></div>\n\t</div>\n\t<div class=\"imtblock\">\n\t\t<div class=\"srcblock\">gwo</div>\n\t\t<div class=\"glossblock\">great</div>\n\t</div>\n\t<div class=\"imtblock\">\n\t\t<div class=\"srcblock\">nouvèl.</div>\n\t\t<div class=\"glossblock\">news</div>\n\t</div>\n</div>\n",
        "imt": "that \\textsc{cop} \\textsc{fut} \\textsc{indf} great news",
        "imtwordsbare": [
            "that",
            "COP",
            "FUT",
            "INDF",
            "great",
            "news"
        ],
        "imtwordstex": [
            "that",
            "\\textsc{cop}",
            "\\textsc{fut}",
            "\\textsc{indf}",
            "great",
            "news"
        ],
        "language": "und",
        "src": "Sa se va yon gwo nouvèl.",
        "srcwordsbare": [
            "Sa",
            "se",
            "va",
            "yon",
            "gwo",
            "nouvèl."
        ],
        "srcwordstex": [
            "Sa",
            "se",
            "va",
            "yon",
            "gwo",
            "nouvèl."
        ],
        "trs": "\\trad{That will be great news.} \\\\",
        "wlength": 6
    },
    {
        "ID": "Kihm--58433",
        "bookID": "165",
        "categories": [
            "cop",
            "indf",
            "prog",
            "pst"
        ],
        "clength": 20,
        "html": "<div class=\"imtblocks\">\n\t<div class=\"imtblock\">\n\t\t<div class=\"srcblock\">Se</div>\n\t\t<div class=\"glossblock\"><span class=\"sc\">cop</span></div>\n\t</div>\n\t<div class=\"imtblock\">\n\t\t<div class=\"srcblock\">tap</div>\n\t\t<div class=\"glossblock\"><span class=\"sc\">pst.prog</span></div>\n\t</div>\n\t<div class=\"imtblock\">\n\t\t<div class=\"srcblock\">yon</div>\n\t\t<div class=\"glossblock\"><span class=\"sc\">indf</span></div>\n\t</div>\n\t<div class=\"imtblock\">\n\t\t<div class=\"srcblock\">tan</div>\n\t\t<div class=\"glossblock\">time</div>\n\t</div>\n\t<div class=\"imtblock\">\n\t\t<div class=\"srcblock\">pèdi.</div>\n\t\t<div class=\"glossblock\">lose</div>\n\t</div>\n</div>\n",
        "imt": "\\textsc{cop} \\textsc{pst.prog} \\textsc{indf} time lose",
        "imtwordsbare": [
            "COP",
            "pst.prog",
            "INDF",
            "time",
            "lose"
        ],
        "imtwordstex": [
            "\\textsc{cop}",
            "\\textsc{pst.prog}",
            "\\textsc{indf}",
            "time",
            "lose"
        ],
        "language": "und",
        "src": "Se tap yon tan pèdi.",
        "srcwordsbare": [
            "Se",
            "tap",
            "yon",
            "tan",
            "pèdi."
        ],
        "srcwordstex": [
            "Se",
            "tap",
            "yon",
            "tan",
            "pèdi."
        ],
        "trs": "\\trad{It would be time lost.} (\\emph{Ce serait une perte de temps}) \\\\",
        "wlength": 5
    },
    {
        "ID": "Kihm--43082",
        "bookID": "165",
        "categories": [
            "1sg",
            "3sg",
            "cop"
        ],
        "clength": 20,
        "html": "<div class=\"imtblocks\">\n\t<div class=\"imtblock\">\n\t\t<div class=\"srcblock\">Li</div>\n\t\t<div class=\"glossblock\"><span class=\"sc\">3sg</span></div>\n\t</div>\n\t<div class=\"imtblock\">\n\t\t<div class=\"srcblock\">se</div>\n\t\t<div class=\"glossblock\"><span class=\"sc\">cop</span></div>\n\t</div>\n\t<div class=\"imtblock\">\n\t\t<div class=\"srcblock\">te</div>\n\t\t<div class=\"glossblock\">{pst}</div>\n\t</div>\n\t<div class=\"imtblock\">\n\t\t<div class=\"srcblock\">zanmi</div>\n\t\t<div class=\"glossblock\">friend</div>\n\t</div>\n\t<div class=\"imtblock\">\n\t\t<div class=\"srcblock\">mwen.</div>\n\t\t<div class=\"glossblock\"><span class=\"sc\">1sg</span></div>\n\t</div>\n</div>\n",
        "imt": "\\textsc{3sg} \\textsc{cop} {pst} friend \\textsc{1sg}",
        "imtwordsbare": [
            "3SG",
            "COP",
            "{pst}",
            "friend",
            "1SG"
        ],
        "imtwordstex": [
            "\\textsc{3sg}",
            "\\textsc{cop}",
            "{pst}",
            "friend",
            "\\textsc{1sg}"
        ],
        "language": "und",
        "src": "Li se te zanmi mwen.",
        "srcwordsbare": [
            "Li",
            "se",
            "te",
            "zanmi",
            "mwen."
        ],
        "srcwordstex": [
            "Li",
            "se",
            "te",
            "zanmi",
            "mwen."
        ],
        "trs": "Intended: \\trad{S/he was my friend.} \\\\}",
        "wlength": 5
    },
    {
        "ID": "Kihm-888403",
        "bookID": "165",
        "categories": [
            "1sg",
            "3sg",
            "cop",
            "pst"
        ],
        "clength": 25,
        "html": "<div class=\"imtblocks\">\n\t<div class=\"imtblock\">\n\t\t<div class=\"srcblock\">Li-mèm,</div>\n\t\t<div class=\"glossblock\"><span class=\"sc\">3sg</span>-self</div>\n\t</div>\n\t<div class=\"imtblock\">\n\t\t<div class=\"srcblock\">se</div>\n\t\t<div class=\"glossblock\"><span class=\"sc\">cop</span></div>\n\t</div>\n\t<div class=\"imtblock\">\n\t\t<div class=\"srcblock\">te</div>\n\t\t<div class=\"glossblock\"><span class=\"sc\">pst</span></div>\n\t</div>\n\t<div class=\"imtblock\">\n\t\t<div class=\"srcblock\">zanmi</div>\n\t\t<div class=\"glossblock\">friend</div>\n\t</div>\n\t<div class=\"imtblock\">\n\t\t<div class=\"srcblock\">mwen.</div>\n\t\t<div class=\"glossblock\"><span class=\"sc\">1sg</span></div>\n\t</div>\n</div>\n",
        "imt": "\\textsc{3sg}-self \\textsc{cop} \\textsc{pst} friend \\textsc{1sg}",
        "imtwordsbare": [
            "3SG-self",
            "COP",
            "PST",
            "friend",
            "1SG"
        ],
        "imtwordstex": [
            "\\textsc{3sg}-self",
            "\\textsc{cop}",
            "\\textsc{pst}",
            "friend",
            "\\textsc{1sg}"
        ],
        "language": "und",
        "src": "Li-mèm, se te zanmi mwen.",
        "srcwordsbare": [
            "Li-mèm,",
            "se",
            "te",
            "zanmi",
            "mwen."
        ],
        "srcwordstex": [
            "Li-mèm,",
            "se",
            "te",
            "zanmi",
            "mwen."
        ],
        "trs": "\\trad{S/he was my friend.} \\\\}",
        "wlength": 5
    },
    {
        "ID": "Kihm-206504",
        "bookID": "165",
        "categories": [
            "cop",
            "indf"
        ],
        "clength": 37,
        "html": "<div class=\"imtblocks\">\n\t<div class=\"imtblock\">\n\t\t<div class=\"srcblock\">Labote</div>\n\t\t<div class=\"glossblock\">beauty</div>\n\t</div>\n\t<div class=\"imtblock\">\n\t\t<div class=\"srcblock\">/</div>\n\t\t<div class=\"glossblock\">{}</div>\n\t</div>\n\t<div class=\"imtblock\">\n\t\t<div class=\"srcblock\">s'</div>\n\t\t<div class=\"glossblock\"><span class=\"sc\">cop</span></div>\n\t</div>\n\t<div class=\"imtblock\">\n\t\t<div class=\"srcblock\">on</div>\n\t\t<div class=\"glossblock\"><span class=\"sc\">indf</span></div>\n\t</div>\n\t<div class=\"imtblock\">\n\t\t<div class=\"srcblock\">zwazo</div>\n\t\t<div class=\"glossblock\">bird</div>\n\t</div>\n\t<div class=\"imtblock\">\n\t\t<div class=\"srcblock\">benyen</div>\n\t\t<div class=\"glossblock\">bath</div>\n\t</div>\n\t<div class=\"imtblock\">\n\t\t<div class=\"srcblock\">an</div>\n\t\t<div class=\"glossblock\">in</div>\n\t</div>\n\t<div class=\"imtblock\">\n\t\t<div class=\"srcblock\">san.</div>\n\t\t<div class=\"glossblock\">blood</div>\n\t</div>\n</div>\n",
        "imt": "beauty {} \\textsc{cop} \\textsc{indf} bird bath in blood",
        "imtwordsbare": [
            "beauty",
            "{}",
            "COP",
            "INDF",
            "bird",
            "bath",
            "in",
            "blood"
        ],
        "imtwordstex": [
            "beauty",
            "{}",
            "\\textsc{cop}",
            "\\textsc{indf}",
            "bird",
            "bath",
            "in",
            "blood"
        ],
        "language": "und",
        "src": "Labote  /  s' on zwazo benyen an san.",
        "srcwordsbare": [
            "Labote",
            "/",
            "s'",
            "on",
            "zwazo",
            "benyen",
            "an",
            "san."
        ],
        "srcwordstex": [
            "Labote",
            "/",
            "s'",
            "on",
            "zwazo",
            "benyen",
            "an",
            "san."
        ],
        "trs": "\\trad{beauty / is a bird bathed in blood.} (\\emph{la beauté} / \\emph{est un oiseau ensanglanté}) \\\\",
        "wlength": 8
    },
    {
        "ID": "Kihm--47771",
        "bookID": "165",
        "categories": [
            "prog"
        ],
        "clength": 13,
        "html": "<div class=\"imtblocks\">\n\t<div class=\"imtblock\">\n\t\t<div class=\"srcblock\">Jan</div>\n\t\t<div class=\"glossblock\">John</div>\n\t</div>\n\t<div class=\"imtblock\">\n\t\t<div class=\"srcblock\">ap</div>\n\t\t<div class=\"glossblock\"><span class=\"sc\">prog</span></div>\n\t</div>\n\t<div class=\"imtblock\">\n\t\t<div class=\"srcblock\">doktè.</div>\n\t\t<div class=\"glossblock\">doctor</div>\n\t</div>\n</div>\n",
        "imt": "John \\textsc{prog} doctor",
        "imtwordsbare": [
            "John",
            "PROG",
            "doctor"
        ],
        "imtwordstex": [
            "John",
            "\\textsc{prog}",
            "doctor"
        ],
        "language": "und",
        "src": "Jan ap doktè.",
        "srcwordsbare": [
            "Jan",
            "ap",
            "doktè."
        ],
        "srcwordstex": [
            "Jan",
            "ap",
            "doktè."
        ],
        "trs": "\\trad{John will be a doctor.} \\\\",
        "wlength": 3
    },
    {
        "ID": "Kihm--62583",
        "bookID": "165",
        "categories": [
            "neg"
        ],
        "clength": 26,
        "html": "<div class=\"imtblocks\">\n\t<div class=\"imtblock\">\n\t\t<div class=\"srcblock\">Duvalye</div>\n\t\t<div class=\"glossblock\">Duvallier</div>\n\t</div>\n\t<div class=\"imtblock\">\n\t\t<div class=\"srcblock\">pa</div>\n\t\t<div class=\"glossblock\"><span class=\"sc\">neg</span></div>\n\t</div>\n\t<div class=\"imtblock\">\n\t\t<div class=\"srcblock\">prezidan</div>\n\t\t<div class=\"glossblock\">president</div>\n\t</div>\n\t<div class=\"imtblock\">\n\t\t<div class=\"srcblock\">Ayiti.</div>\n\t\t<div class=\"glossblock\">Haiti</div>\n\t</div>\n</div>\n",
        "imt": "Duvallier \\textsc{neg} president Haiti",
        "imtwordsbare": [
            "Duvallier",
            "NEG",
            "president",
            "Haiti"
        ],
        "imtwordstex": [
            "Duvallier",
            "\\textsc{neg}",
            "president",
            "Haiti"
        ],
        "language": "und",
        "src": "Duvalye pa prezidan Ayiti.",
        "srcwordsbare": [
            "Duvalye",
            "pa",
            "prezidan",
            "Ayiti."
        ],
        "srcwordstex": [
            "Duvalye",
            "pa",
            "prezidan",
            "Ayiti."
        ],
        "trs": "\\trad{Duvallier isn't the president of Haiti.} \\\\",
        "wlength": 4
    },
    {
        "ID": "Kihm--89417",
        "bookID": "165",
        "categories": [
            "(neg)",
            "(pst)",
            "def"
        ],
        "clength": 71,
        "html": "<div class=\"imtblocks\">\n\t<div class=\"imtblock\">\n\t\t<div class=\"srcblock\">Jan</div>\n\t\t<div class=\"glossblock\">John</div>\n\t</div>\n\t<div class=\"imtblock\">\n\t\t<div class=\"srcblock\">(pa)</div>\n\t\t<div class=\"glossblock\"><span class=\"sc\">(neg)</span></div>\n\t</div>\n\t<div class=\"imtblock\">\n\t\t<div class=\"srcblock\">(te)</div>\n\t\t<div class=\"glossblock\"><span class=\"sc\">(pst)</span></div>\n\t</div>\n\t<div class=\"imtblock\">\n\t\t<div class=\"srcblock\">(bon)</div>\n\t\t<div class=\"glossblock\">(good)</div>\n\t</div>\n\t<div class=\"imtblock\">\n\t\t<div class=\"srcblock\">chapantyè</div>\n\t\t<div class=\"glossblock\">carpenter</div>\n\t</div>\n\t<div class=\"imtblock\">\n\t\t<div class=\"srcblock\">/</div>\n\t\t<div class=\"glossblock\">{}</div>\n\t</div>\n\t<div class=\"imtblock\">\n\t\t<div class=\"srcblock\">malad</div>\n\t\t<div class=\"glossblock\">sick</div>\n\t</div>\n\t<div class=\"imtblock\">\n\t\t<div class=\"srcblock\">(anpil)</div>\n\t\t<div class=\"glossblock\">(very)</div>\n\t</div>\n\t<div class=\"imtblock\">\n\t\t<div class=\"srcblock\">/</div>\n\t\t<div class=\"glossblock\">{}</div>\n\t</div>\n\t<div class=\"imtblock\">\n\t\t<div class=\"srcblock\">nan</div>\n\t\t<div class=\"glossblock\">in</div>\n\t</div>\n\t<div class=\"imtblock\">\n\t\t<div class=\"srcblock\">lekol</div>\n\t\t<div class=\"glossblock\">school</div>\n\t</div>\n\t<div class=\"imtblock\">\n\t\t<div class=\"srcblock\">la</div>\n\t\t<div class=\"glossblock\"><span class=\"sc\">def</span></div>\n\t</div>\n\t<div class=\"imtblock\">\n\t\t<div class=\"srcblock\">/</div>\n\t\t<div class=\"glossblock\">{}</div>\n\t</div>\n\t<div class=\"imtblock\">\n\t\t<div class=\"srcblock\">konsa.</div>\n\t\t<div class=\"glossblock\">so</div>\n\t</div>\n</div>\n",
        "imt": "John \\textsc{(neg)}  \\textsc{(pst)} (good) carpenter {} sick (very) {} in school \\textsc{def} {} so",
        "imtwordsbare": [
            "John",
            "(neg)",
            "(pst)",
            "(good)",
            "carpenter",
            "{}",
            "sick",
            "(very)",
            "{}",
            "in",
            "school",
            "DEF",
            "{}",
            "so"
        ],
        "imtwordstex": [
            "John",
            "\\textsc{(neg)}",
            "\\textsc{(pst)}",
            "(good)",
            "carpenter",
            "{}",
            "sick",
            "(very)",
            "{}",
            "in",
            "school",
            "\\textsc{def}",
            "{}",
            "so"
        ],
        "language": "und",
        "src": "Jan (pa) (te) (bon) chapantyè  /  malad (anpil) / nan lekol la / konsa.",
        "srcwordsbare": [
            "Jan",
            "(pa)",
            "(te)",
            "(bon)",
            "chapantyè",
            "/",
            "malad",
            "(anpil)",
            "/",
            "nan",
            "lekol",
            "la",
            "/",
            "konsa."
        ],
        "srcwordstex": [
            "Jan",
            "(pa)",
            "(te)",
            "(bon)",
            "chapantyè",
            "/",
            "malad",
            "(anpil)",
            "/",
            "nan",
            "lekol",
            "la",
            "/",
            "konsa."
        ],
        "trs": "\\trad{John is/was (not) a (good) carpenter/(very) sick/at school/so.} \\\\",
        "wlength": 14
    },
    {
        "ID": "Kihm-392498",
        "bookID": "165",
        "categories": [
            "2sg",
            "cop",
            "indf"
        ],
        "clength": 51,
        "html": "<div class=\"imtblocks\">\n\t<div class=\"imtblock\">\n\t\t<div class=\"srcblock\">Mari</div>\n\t\t<div class=\"glossblock\">Mary</div>\n\t</div>\n\t<div class=\"imtblock\">\n\t\t<div class=\"srcblock\">se</div>\n\t\t<div class=\"glossblock\"><span class=\"sc\">cop</span></div>\n\t</div>\n\t<div class=\"imtblock\">\n\t\t<div class=\"srcblock\">yon</div>\n\t\t<div class=\"glossblock\"><span class=\"sc\">indf</span></div>\n\t</div>\n\t<div class=\"imtblock\">\n\t\t<div class=\"srcblock\">(bon)</div>\n\t\t<div class=\"glossblock\">(good)</div>\n\t</div>\n\t<div class=\"imtblock\">\n\t\t<div class=\"srcblock\">profesè</div>\n\t\t<div class=\"glossblock\">teacher</div>\n\t</div>\n\t<div class=\"imtblock\">\n\t\t<div class=\"srcblock\">/</div>\n\t\t<div class=\"glossblock\">{}</div>\n\t</div>\n\t<div class=\"imtblock\">\n\t\t<div class=\"srcblock\">fanm</div>\n\t\t<div class=\"glossblock\">woman</div>\n\t</div>\n\t<div class=\"imtblock\">\n\t\t<div class=\"srcblock\">/</div>\n\t\t<div class=\"glossblock\">{}</div>\n\t</div>\n\t<div class=\"imtblock\">\n\t\t<div class=\"srcblock\">sè</div>\n\t\t<div class=\"glossblock\">sister</div>\n\t</div>\n\t<div class=\"imtblock\">\n\t\t<div class=\"srcblock\">ou</div>\n\t\t<div class=\"glossblock\"><span class=\"sc\">2sg</span></div>\n\t</div>\n\t<div class=\"imtblock\">\n\t\t<div class=\"srcblock\">/</div>\n\t\t<div class=\"glossblock\">{}</div>\n\t</div>\n\t<div class=\"imtblock\">\n\t\t<div class=\"srcblock\">malad.</div>\n\t\t<div class=\"glossblock\">sick</div>\n\t</div>\n</div>\n",
        "imt": "Mary \\textsc{cop} \\textsc{indf} (good) teacher {} woman {} sister \\textsc{2sg} {} sick",
        "imtwordsbare": [
            "Mary",
            "COP",
            "INDF",
            "(good)",
            "teacher",
            "{}",
            "woman",
            "{}",
            "sister",
            "2SG",
            "{}",
            "sick"
        ],
        "imtwordstex": [
            "Mary",
            "\\textsc{cop}",
            "\\textsc{indf}",
            "(good)",
            "teacher",
            "{}",
            "woman",
            "{}",
            "sister",
            "\\textsc{2sg}",
            "{}",
            "sick"
        ],
        "language": "und",
        "src": "Mari se yon (bon) profesè  /  fanm / sè ou / malad.",
        "srcwordsbare": [
            "Mari",
            "se",
            "yon",
            "(bon)",
            "profesè",
            "/",
            "fanm",
            "/",
            "sè",
            "ou",
            "/",
            "malad."
        ],
        "srcwordstex": [
            "Mari",
            "se",
            "yon",
            "(bon)",
            "profesè",
            "/",
            "fanm",
            "/",
            "sè",
            "ou",
            "/",
            "malad."
        ],
        "trs": "\\trad{Mary is a (good) teacher / a woman/ your sister / a sick person.} \\\\",
        "wlength": 12
    },
    {
        "ID": "Kihm--47799",
        "bookID": "165",
        "categories": [
            "cop",
            "indf"
        ],
        "clength": 33,
        "html": "<div class=\"imtblocks\">\n\t<div class=\"imtblock\">\n\t\t<div class=\"srcblock\">Se</div>\n\t\t<div class=\"glossblock\"><span class=\"sc\">cop</span></div>\n\t</div>\n\t<div class=\"imtblock\">\n\t\t<div class=\"srcblock\">vre</div>\n\t\t<div class=\"glossblock\">true</div>\n\t</div>\n\t<div class=\"imtblock\">\n\t\t<div class=\"srcblock\">/</div>\n\t\t<div class=\"glossblock\">{}</div>\n\t</div>\n\t<div class=\"imtblock\">\n\t\t<div class=\"srcblock\">konsa</div>\n\t\t<div class=\"glossblock\">so</div>\n\t</div>\n\t<div class=\"imtblock\">\n\t\t<div class=\"srcblock\">/</div>\n\t\t<div class=\"glossblock\">{}</div>\n\t</div>\n\t<div class=\"imtblock\">\n\t\t<div class=\"srcblock\">yon</div>\n\t\t<div class=\"glossblock\"><span class=\"sc\">indf</span></div>\n\t</div>\n\t<div class=\"imtblock\">\n\t\t<div class=\"srcblock\">lòt</div>\n\t\t<div class=\"glossblock\">other</div>\n\t</div>\n\t<div class=\"imtblock\">\n\t\t<div class=\"srcblock\">bagay.</div>\n\t\t<div class=\"glossblock\">thing</div>\n\t</div>\n</div>\n",
        "imt": "\\textsc{cop} true {} so {} \\textsc{indf} other thing",
        "imtwordsbare": [
            "COP",
            "true",
            "{}",
            "so",
            "{}",
            "INDF",
            "other",
            "thing"
        ],
        "imtwordstex": [
            "\\textsc{cop}",
            "true",
            "{}",
            "so",
            "{}",
            "\\textsc{indf}",
            "other",
            "thing"
        ],
        "language": "und",
        "src": "Se vre  /  konsa / yon lòt bagay.",
        "srcwordsbare": [
            "Se",
            "vre",
            "/",
            "konsa",
            "/",
            "yon",
            "lòt",
            "bagay."
        ],
        "srcwordstex": [
            "Se",
            "vre",
            "/",
            "konsa",
            "/",
            "yon",
            "lòt",
            "bagay."
        ],
        "trs": "\\trad{It's true / so / another thing.} \\\\",
        "wlength": 8
    },
    {
        "ID": "Kihm-568166",
        "bookID": "165",
        "categories": [
            "1sg cop"
        ],
        "clength": 26,
        "html": "<div class=\"imtblocks\">\n\t<div class=\"imtblock\">\n\t\t<div class=\"srcblock\">Vi</div>\n\t\t<div class=\"glossblock\">life</div>\n\t</div>\n\t<div class=\"imtblock\">\n\t\t<div class=\"srcblock\">mwen</div>\n\t\t<div class=\"glossblock\">\\textsc{1sg</div>\n\t</div>\n\t<div class=\"imtblock\">\n\t\t<div class=\"srcblock\">se</div>\n\t\t<div class=\"glossblock\">cop}</div>\n\t</div>\n\t<div class=\"imtblock\">\n\t\t<div class=\"srcblock\">nan</div>\n\t\t<div class=\"glossblock\">in</div>\n\t</div>\n\t<div class=\"imtblock\">\n\t\t<div class=\"srcblock\">navigasyon.</div>\n\t\t<div class=\"glossblock\">navigation</div>\n\t</div>\n</div>\n",
        "imt": "life \\textsc{1sg cop} in navigation",
        "imtwordsbare": [
            "life",
            "\\textsc{1sg",
            "cop}",
            "in",
            "navigation"
        ],
        "imtwordstex": [
            "life",
            "\\textsc{1sg",
            "cop}",
            "in",
            "navigation"
        ],
        "language": "und",
        "src": "Vi mwen se nan navigasyon.",
        "srcwordsbare": [
            "Vi",
            "mwen",
            "se",
            "nan",
            "navigasyon."
        ],
        "srcwordstex": [
            "Vi",
            "mwen",
            "se",
            "nan",
            "navigasyon."
        ],
        "trs": "\\trad{My life is in navigation.} \\\\",
        "wlength": 5
    },
    {
        "ID": "Kihm--86257",
        "bookID": "165",
        "categories": [
            "cop",
            "def"
        ],
        "clength": 27,
        "html": "<div class=\"imtblocks\">\n\t<div class=\"imtblock\">\n\t\t<div class=\"srcblock\">Se</div>\n\t\t<div class=\"glossblock\"><span class=\"sc\">cop</span></div>\n\t</div>\n\t<div class=\"imtblock\">\n\t\t<div class=\"srcblock\">kraze</div>\n\t\t<div class=\"glossblock\">destroy</div>\n\t</div>\n\t<div class=\"imtblock\">\n\t\t<div class=\"srcblock\">Bouki</div>\n\t\t<div class=\"glossblock\">B.</div>\n\t</div>\n\t<div class=\"imtblock\">\n\t\t<div class=\"srcblock\">kraze</div>\n\t\t<div class=\"glossblock\">destroy</div>\n\t</div>\n\t<div class=\"imtblock\">\n\t\t<div class=\"srcblock\">kay</div>\n\t\t<div class=\"glossblock\">house</div>\n\t</div>\n\t<div class=\"imtblock\">\n\t\t<div class=\"srcblock\">la</div>\n\t\t<div class=\"glossblock\"><span class=\"sc\">def</span></div>\n\t</div>\n</div>\n",
        "imt": "\\textsc{cop} destroy B. destroy house \\textsc{def}",
        "imtwordsbare": [
            "COP",
            "destroy",
            "B.",
            "destroy",
            "house",
            "DEF"
        ],
        "imtwordstex": [
            "\\textsc{cop}",
            "destroy",
            "B.",
            "destroy",
            "house",
            "\\textsc{def}"
        ],
        "language": "und",
        "src": "Se kraze Bouki kraze kay la",
        "srcwordsbare": [
            "Se",
            "kraze",
            "Bouki",
            "kraze",
            "kay",
            "la"
        ],
        "srcwordstex": [
            "Se",
            "kraze",
            "Bouki",
            "kraze",
            "kay",
            "la"
        ],
        "trs": "\\trad{What Bouki did to the house was destroy it.}}",
        "wlength": 6
    },
    {
        "ID": "Kihm--58365",
        "bookID": "165",
        "categories": [
            "cop",
            "def",
            "dem"
        ],
        "clength": 31,
        "html": "<div class=\"imtblocks\">\n\t<div class=\"imtblock\">\n\t\t<div class=\"srcblock\">Se</div>\n\t\t<div class=\"glossblock\"><span class=\"sc\">cop</span></div>\n\t</div>\n\t<div class=\"imtblock\">\n\t\t<div class=\"srcblock\">konnen</div>\n\t\t<div class=\"glossblock\">know</div>\n\t</div>\n\t<div class=\"imtblock\">\n\t\t<div class=\"srcblock\">Jan</div>\n\t\t<div class=\"glossblock\">J.</div>\n\t</div>\n\t<div class=\"imtblock\">\n\t\t<div class=\"srcblock\">konnen</div>\n\t\t<div class=\"glossblock\">know</div>\n\t</div>\n\t<div class=\"imtblock\">\n\t\t<div class=\"srcblock\">lang</div>\n\t\t<div class=\"glossblock\">language</div>\n\t</div>\n\t<div class=\"imtblock\">\n\t\t<div class=\"srcblock\">sa</div>\n\t\t<div class=\"glossblock\"><span class=\"sc\">dem</span></div>\n\t</div>\n\t<div class=\"imtblock\">\n\t\t<div class=\"srcblock\">a.</div>\n\t\t<div class=\"glossblock\"><span class=\"sc\">def</span></div>\n\t</div>\n</div>\n",
        "imt": "\\textsc{cop} know J. know language \\textsc{dem} \\textsc{def}",
        "imtwordsbare": [
            "COP",
            "know",
            "J.",
            "know",
            "language",
            "DEM",
            "DEF"
        ],
        "imtwordstex": [
            "\\textsc{cop}",
            "know",
            "J.",
            "know",
            "language",
            "\\textsc{dem}",
            "\\textsc{def}"
        ],
        "language": "und",
        "src": "Se konnen Jan konnen lang sa a.",
        "srcwordsbare": [
            "Se",
            "konnen",
            "Jan",
            "konnen",
            "lang",
            "sa",
            "a."
        ],
        "srcwordstex": [
            "Se",
            "konnen",
            "Jan",
            "konnen",
            "lang",
            "sa",
            "a."
        ],
        "trs": "Intended: \\trad{John does know that language.}}",
        "wlength": 7
    }
]