[
    {
        "ID": "egerland-851501",
        "abbrkey": {},
        "book_ID": 115,
        "book_URL": "https://langsci-press.org/catalog/book/115",
        "book_metalanguage": "eng",
        "book_title": "Order and structure in syntax II",
        "categories": [
            "si"
        ],
        "citation": null,
        "clength": 68,
        "entities": [],
        "html": "<div class=\"imtblocks\">\n\t<div class=\"imtblock\">\n\t\t<div class=\"srcblock\">Si</div>\n\t\t<div class=\"glossblock\"><span class=\"sc\">si</span></div>\n\t</div>\n\t<div class=\"imtblock\">\n\t\t<div class=\"srcblock\">è</div>\n\t\t<div class=\"glossblock\">is</div>\n\t</div>\n\t<div class=\"imtblock\">\n\t\t<div class=\"srcblock\">lavorato</div>\n\t\t<div class=\"glossblock\">worked</div>\n\t</div>\n\t<div class=\"imtblock\">\n\t\t<div class=\"srcblock\">per</div>\n\t\t<div class=\"glossblock\">for</div>\n\t</div>\n\t<div class=\"imtblock\">\n\t\t<div class=\"srcblock\">due</div>\n\t\t<div class=\"glossblock\">two</div>\n\t</div>\n\t<div class=\"imtblock\">\n\t\t<div class=\"srcblock\">mesi</div>\n\t\t<div class=\"glossblock\">months</div>\n\t</div>\n\t<div class=\"imtblock\">\n\t\t<div class=\"srcblock\">per</div>\n\t\t<div class=\"glossblock\">for</div>\n\t</div>\n\t<div class=\"imtblock\">\n\t\t<div class=\"srcblock\">risolvere</div>\n\t\t<div class=\"glossblock\">solve</div>\n\t</div>\n\t<div class=\"imtblock\">\n\t\t<div class=\"srcblock\">il</div>\n\t\t<div class=\"glossblock\">the</div>\n\t</div>\n\t<div class=\"imtblock\">\n\t\t<div class=\"srcblock\">problema.</div>\n\t\t<div class=\"glossblock\">problem</div>\n\t</div>\n</div>\n",
        "imtwordsbare": [
            "SI",
            "is",
            "worked",
            "for",
            "two",
            "months",
            "for",
            "solve",
            "the",
            "problem"
        ],
        "label": "Si è lavorato per due mesi per risolvere il problema.",
        "language": "https://glottolog.org/resource/languoid/id/ital1282",
        "language_glottocode": "ital1282",
        "language_iso6393": null,
        "language_name": null,
        "parententities": [],
        "srcwordsbare": [
            "Si",
            "è",
            "lavorato",
            "per",
            "due",
            "mesi",
            "per",
            "risolvere",
            "il",
            "problema."
        ],
        "trs": "a. ‘People have worked for two months to solve the problem.",
        "wlength": 10
    },
    {
        "ID": "egerland-874660",
        "abbrkey": {},
        "book_ID": 115,
        "book_URL": "https://langsci-press.org/catalog/book/115",
        "book_metalanguage": "eng",
        "book_title": "Order and structure in syntax II",
        "categories": [
            "si"
        ],
        "citation": null,
        "clength": 35,
        "entities": [],
        "html": "<div class=\"imtblocks\">\n\t<div class=\"imtblock\">\n\t\t<div class=\"srcblock\">Ieri</div>\n\t\t<div class=\"glossblock\">yesterday</div>\n\t</div>\n\t<div class=\"imtblock\">\n\t\t<div class=\"srcblock\">si</div>\n\t\t<div class=\"glossblock\"><span class=\"sc\">si</span></div>\n\t</div>\n\t<div class=\"imtblock\">\n\t\t<div class=\"srcblock\">è</div>\n\t\t<div class=\"glossblock\">is</div>\n\t</div>\n\t<div class=\"imtblock\">\n\t\t<div class=\"srcblock\">stati</div>\n\t\t<div class=\"glossblock\">been</div>\n\t</div>\n\t<div class=\"imtblock\">\n\t\t<div class=\"srcblock\">licenziati.</div>\n\t\t<div class=\"glossblock\">fired</div>\n\t</div>\n</div>\n",
        "imtwordsbare": [
            "yesterday",
            "SI",
            "is",
            "been",
            "fired"
        ],
        "label": "Ieri si è stati licenziati.",
        "language": "https://glottolog.org/resource/languoid/id/ital1282",
        "language_glottocode": "ital1282",
        "language_iso6393": null,
        "language_name": null,
        "parententities": [],
        "srcwordsbare": [
            "Ieri",
            "si",
            "è",
            "stati",
            "licenziati."
        ],
        "trs": "yesterday we were fired",
        "wlength": 5
    },
    {
        "ID": "egerland--65054",
        "abbrkey": {},
        "book_ID": 115,
        "book_URL": "https://langsci-press.org/catalog/book/115",
        "book_metalanguage": "eng",
        "book_title": "Order and structure in syntax II",
        "categories": [
            "man"
        ],
        "citation": null,
        "clength": 62,
        "entities": [],
        "html": "<div class=\"imtblocks\">\n\t<div class=\"imtblock\">\n\t\t<div class=\"srcblock\">Als</div>\n\t\t<div class=\"glossblock\">when</div>\n\t</div>\n\t<div class=\"imtblock\">\n\t\t<div class=\"srcblock\">ich</div>\n\t\t<div class=\"glossblock\">I</div>\n\t</div>\n\t<div class=\"imtblock\">\n\t\t<div class=\"srcblock\">klein</div>\n\t\t<div class=\"glossblock\">little</div>\n\t</div>\n\t<div class=\"imtblock\">\n\t\t<div class=\"srcblock\">war,</div>\n\t\t<div class=\"glossblock\">was</div>\n\t</div>\n\t<div class=\"imtblock\">\n\t\t<div class=\"srcblock\">wurde</div>\n\t\t<div class=\"glossblock\">got</div>\n\t</div>\n\t<div class=\"imtblock\">\n\t\t<div class=\"srcblock\">man</div>\n\t\t<div class=\"glossblock\"><span class=\"sc\">man</span></div>\n\t</div>\n\t<div class=\"imtblock\">\n\t\t<div class=\"srcblock\">nur</div>\n\t\t<div class=\"glossblock\">only</div>\n\t</div>\n\t<div class=\"imtblock\">\n\t\t<div class=\"srcblock\">am</div>\n\t\t<div class=\"glossblock\">on</div>\n\t</div>\n\t<div class=\"imtblock\">\n\t\t<div class=\"srcblock\">Freitag</div>\n\t\t<div class=\"glossblock\">Friday</div>\n\t</div>\n\t<div class=\"imtblock\">\n\t\t<div class=\"srcblock\">gebadet.</div>\n\t\t<div class=\"glossblock\">bathed</div>\n\t</div>\n</div>\n",
        "imtwordsbare": [
            "when",
            "I",
            "little",
            "was",
            "got",
            "MAN",
            "only",
            "on",
            "Friday",
            "bathed"
        ],
        "label": "Als ich klein war, wurde man nur am Freitag gebadet.",
        "language": "https://glottolog.org/resource/languoid/id/stan1295",
        "language_glottocode": "stan1295",
        "language_iso6393": null,
        "language_name": null,
        "parententities": [],
        "srcwordsbare": [
            "Als",
            "ich",
            "klein",
            "war,",
            "wurde",
            "man",
            "nur",
            "am",
            "Freitag",
            "gebadet."
        ],
        "trs": "When I was little, we only had a bath on Fridays.",
        "wlength": 10
    },
    {
        "ID": "egerland-254539",
        "abbrkey": {},
        "book_ID": 115,
        "book_URL": "https://langsci-press.org/catalog/book/115",
        "book_metalanguage": "eng",
        "book_title": "Order and structure in syntax II",
        "categories": [],
        "citation": null,
        "clength": 68,
        "entities": [],
        "html": "<div class=\"imtblocks\">\n\t<div class=\"imtblock\">\n\t\t<div class=\"srcblock\">Wenn</div>\n\t\t<div class=\"glossblock\">If</div>\n\t</div>\n\t<div class=\"imtblock\">\n\t\t<div class=\"srcblock\">ich</div>\n\t\t<div class=\"glossblock\">I</div>\n\t</div>\n\t<div class=\"imtblock\">\n\t\t<div class=\"srcblock\">Kinder</div>\n\t\t<div class=\"glossblock\">kids</div>\n\t</div>\n\t<div class=\"imtblock\">\n\t\t<div class=\"srcblock\">hätte,</div>\n\t\t<div class=\"glossblock\">had</div>\n\t</div>\n\t<div class=\"imtblock\">\n\t\t<div class=\"srcblock\">könnte</div>\n\t\t<div class=\"glossblock\">could</div>\n\t</div>\n\t<div class=\"imtblock\">\n\t\t<div class=\"srcblock\">man</div>\n\t\t<div class=\"glossblock\">man</div>\n\t</div>\n\t<div class=\"imtblock\">\n\t\t<div class=\"srcblock\">zusammen</div>\n\t\t<div class=\"glossblock\">together</div>\n\t</div>\n\t<div class=\"imtblock\">\n\t\t<div class=\"srcblock\">Monopoly</div>\n\t\t<div class=\"glossblock\">Monopoly</div>\n\t</div>\n\t<div class=\"imtblock\">\n\t\t<div class=\"srcblock\">spielen.</div>\n\t\t<div class=\"glossblock\">play.</div>\n\t</div>\n</div>\n",
        "imtwordsbare": [
            "If",
            "I",
            "kids",
            "had",
            "could",
            "man",
            "together",
            "Monopoly",
            "play."
        ],
        "label": "Wenn ich Kinder hätte, könnte man zusammen Monopoly spielen.",
        "language": "https://glottolog.org/resource/languoid/id/stan1295",
        "language_glottocode": "stan1295",
        "language_iso6393": null,
        "language_name": null,
        "parententities": [],
        "srcwordsbare": [
            "Wenn",
            "ich",
            "Kinder",
            "hätte,",
            "könnte",
            "man",
            "zusammen",
            "Monopoly",
            "spielen."
        ],
        "trs": "If I had children, we could play Monopoly together.",
        "wlength": 9
    },
    {
        "ID": "egerland-441205",
        "abbrkey": {},
        "book_ID": 115,
        "book_URL": "https://langsci-press.org/catalog/book/115",
        "book_metalanguage": "eng",
        "book_title": "Order and structure in syntax II",
        "categories": [
            "man"
        ],
        "citation": null,
        "clength": 54,
        "entities": [],
        "html": "<div class=\"imtblocks\">\n\t<div class=\"imtblock\">\n\t\t<div class=\"srcblock\">När</div>\n\t\t<div class=\"glossblock\">when</div>\n\t</div>\n\t<div class=\"imtblock\">\n\t\t<div class=\"srcblock\">jag</div>\n\t\t<div class=\"glossblock\">I</div>\n\t</div>\n\t<div class=\"imtblock\">\n\t\t<div class=\"srcblock\">var</div>\n\t\t<div class=\"glossblock\">was</div>\n\t</div>\n\t<div class=\"imtblock\">\n\t\t<div class=\"srcblock\">liten</div>\n\t\t<div class=\"glossblock\">little</div>\n\t</div>\n\t<div class=\"imtblock\">\n\t\t<div class=\"srcblock\">badade</div>\n\t\t<div class=\"glossblock\">bathed</div>\n\t</div>\n\t<div class=\"imtblock\">\n\t\t<div class=\"srcblock\">man</div>\n\t\t<div class=\"glossblock\"><span class=\"sc\">man</span></div>\n\t</div>\n\t<div class=\"imtblock\">\n\t\t<div class=\"srcblock\">bara</div>\n\t\t<div class=\"glossblock\">only</div>\n\t</div>\n\t<div class=\"imtblock\">\n\t\t<div class=\"srcblock\">på</div>\n\t\t<div class=\"glossblock\">on</div>\n\t</div>\n\t<div class=\"imtblock\">\n\t\t<div class=\"srcblock\">fredagar.</div>\n\t\t<div class=\"glossblock\">Fridays</div>\n\t</div>\n</div>\n",
        "imtwordsbare": [
            "when",
            "I",
            "was",
            "little",
            "bathed",
            "MAN",
            "only",
            "on",
            "Fridays"
        ],
        "label": "När jag var liten badade man bara på fredagar.",
        "language": "https://glottolog.org/resource/languoid/id/swed1254",
        "language_glottocode": "swed1254",
        "language_iso6393": null,
        "language_name": null,
        "parententities": [],
        "srcwordsbare": [
            "När",
            "jag",
            "var",
            "liten",
            "badade",
            "man",
            "bara",
            "på",
            "fredagar."
        ],
        "trs": "When I was little, we only had a bath on Fridays.",
        "wlength": 9
    },
    {
        "ID": "egerland-533814",
        "abbrkey": {},
        "book_ID": 115,
        "book_URL": "https://langsci-press.org/catalog/book/115",
        "book_metalanguage": "eng",
        "book_title": "Order and structure in syntax II",
        "categories": [
            "man"
        ],
        "citation": null,
        "clength": 36,
        "entities": [
            {
                "label": "Spain",
                "wdid": "Q29"
            }
        ],
        "html": "<div class=\"imtblocks\">\n\t<div class=\"imtblock\">\n\t\t<div class=\"srcblock\">I</div>\n\t\t<div class=\"glossblock\">In</div>\n\t</div>\n\t<div class=\"imtblock\">\n\t\t<div class=\"srcblock\">Spanien</div>\n\t\t<div class=\"glossblock\">Spain</div>\n\t</div>\n\t<div class=\"imtblock\">\n\t\t<div class=\"srcblock\">äter</div>\n\t\t<div class=\"glossblock\">eats</div>\n\t</div>\n\t<div class=\"imtblock\">\n\t\t<div class=\"srcblock\">man</div>\n\t\t<div class=\"glossblock\"><span class=\"sc\">man</span></div>\n\t</div>\n\t<div class=\"imtblock\">\n\t\t<div class=\"srcblock\">middag</div>\n\t\t<div class=\"glossblock\">dinner</div>\n\t</div>\n\t<div class=\"imtblock\">\n\t\t<div class=\"srcblock\">sent.</div>\n\t\t<div class=\"glossblock\">late</div>\n\t</div>\n</div>\n",
        "imtwordsbare": [
            "In",
            "Spain",
            "eats",
            "MAN",
            "dinner",
            "late"
        ],
        "label": "I Spanien äter man middag sent.",
        "language": "https://glottolog.org/resource/languoid/id/swed1254",
        "language_glottocode": "swed1254",
        "language_iso6393": null,
        "language_name": null,
        "parententities": [],
        "srcwordsbare": [
            "I",
            "Spanien",
            "äter",
            "man",
            "middag",
            "sent."
        ],
        "trs": "a. ‘In Spain people have dinner late",
        "wlength": 6
    },
    {
        "ID": "egerland--73894",
        "abbrkey": {},
        "book_ID": 115,
        "book_URL": "https://langsci-press.org/catalog/book/115",
        "book_metalanguage": "eng",
        "book_title": "Order and structure in syntax II",
        "categories": [
            "si"
        ],
        "citation": null,
        "clength": 30,
        "entities": [
            {
                "label": "Spain",
                "wdid": "Q29"
            }
        ],
        "html": "<div class=\"imtblocks\">\n\t<div class=\"imtblock\">\n\t\t<div class=\"srcblock\">In</div>\n\t\t<div class=\"glossblock\">In</div>\n\t</div>\n\t<div class=\"imtblock\">\n\t\t<div class=\"srcblock\">Spagna</div>\n\t\t<div class=\"glossblock\">Spain</div>\n\t</div>\n\t<div class=\"imtblock\">\n\t\t<div class=\"srcblock\">si</div>\n\t\t<div class=\"glossblock\"><span class=\"sc\">si</span></div>\n\t</div>\n\t<div class=\"imtblock\">\n\t\t<div class=\"srcblock\">mangia</div>\n\t\t<div class=\"glossblock\">eats</div>\n\t</div>\n\t<div class=\"imtblock\">\n\t\t<div class=\"srcblock\">tardi.</div>\n\t\t<div class=\"glossblock\">late</div>\n\t</div>\n</div>\n",
        "imtwordsbare": [
            "In",
            "Spain",
            "SI",
            "eats",
            "late"
        ],
        "label": "In Spagna si mangia tardi.",
        "language": "https://glottolog.org/resource/languoid/id/ital1282",
        "language_glottocode": "ital1282",
        "language_iso6393": null,
        "language_name": null,
        "parententities": [],
        "srcwordsbare": [
            "In",
            "Spagna",
            "si",
            "mangia",
            "tardi."
        ],
        "trs": "a.  ‘In Spain people have dinner late",
        "wlength": 5
    },
    {
        "ID": "egerland-555705",
        "abbrkey": {},
        "book_ID": 115,
        "book_URL": "https://langsci-press.org/catalog/book/115",
        "book_metalanguage": "eng",
        "book_title": "Order and structure in syntax II",
        "categories": [
            "man"
        ],
        "citation": null,
        "clength": 40,
        "entities": [],
        "html": "<div class=\"imtblocks\">\n\t<div class=\"imtblock\">\n\t\t<div class=\"srcblock\">Man</div>\n\t\t<div class=\"glossblock\"><span class=\"sc\">man</span></div>\n\t</div>\n\t<div class=\"imtblock\">\n\t\t<div class=\"srcblock\">arbetat</div>\n\t\t<div class=\"glossblock\">works</div>\n\t</div>\n\t<div class=\"imtblock\">\n\t\t<div class=\"srcblock\">för</div>\n\t\t<div class=\"glossblock\">too</div>\n\t</div>\n\t<div class=\"imtblock\">\n\t\t<div class=\"srcblock\">mycket</div>\n\t\t<div class=\"glossblock\">much</div>\n\t</div>\n\t<div class=\"imtblock\">\n\t\t<div class=\"srcblock\">nuförtiden.</div>\n\t\t<div class=\"glossblock\">nowadays</div>\n\t</div>\n</div>\n",
        "imtwordsbare": [
            "MAN",
            "works",
            "too",
            "much",
            "nowadays"
        ],
        "label": "Man arbetat för mycket nuförtiden.",
        "language": "https://glottolog.org/resource/languoid/id/swed1254",
        "language_glottocode": "swed1254",
        "language_iso6393": null,
        "language_name": null,
        "parententities": [],
        "srcwordsbare": [
            "Man",
            "arbetat",
            "för",
            "mycket",
            "nuförtiden."
        ],
        "trs": "People/I have work too much nowadays.",
        "wlength": 5
    },
    {
        "ID": "egerland--69930",
        "abbrkey": {},
        "book_ID": 115,
        "book_URL": "https://langsci-press.org/catalog/book/115",
        "book_metalanguage": "eng",
        "book_title": "Order and structure in syntax II",
        "categories": [
            "man"
        ],
        "citation": null,
        "clength": 40,
        "entities": [],
        "html": "<div class=\"imtblocks\">\n\t<div class=\"imtblock\">\n\t\t<div class=\"srcblock\">Man</div>\n\t\t<div class=\"glossblock\"><span class=\"sc\">man</span></div>\n\t</div>\n\t<div class=\"imtblock\">\n\t\t<div class=\"srcblock\">blir</div>\n\t\t<div class=\"glossblock\">is</div>\n\t</div>\n\t<div class=\"imtblock\">\n\t\t<div class=\"srcblock\">lätt</div>\n\t\t<div class=\"glossblock\">easily</div>\n\t</div>\n\t<div class=\"imtblock\">\n\t\t<div class=\"srcblock\">avskedad</div>\n\t\t<div class=\"glossblock\">fired</div>\n\t</div>\n\t<div class=\"imtblock\">\n\t\t<div class=\"srcblock\">nuförtiden.</div>\n\t\t<div class=\"glossblock\">nowadays</div>\n\t</div>\n</div>\n",
        "imtwordsbare": [
            "MAN",
            "is",
            "easily",
            "fired",
            "nowadays"
        ],
        "label": "Man blir lätt avskedad nuförtiden.",
        "language": "https://glottolog.org/resource/languoid/id/swed1254",
        "language_glottocode": "swed1254",
        "language_iso6393": null,
        "language_name": null,
        "parententities": [],
        "srcwordsbare": [
            "Man",
            "blir",
            "lätt",
            "avskedad",
            "nuförtiden."
        ],
        "trs": "People / I get fired easily nowadays.",
        "wlength": 5
    },
    {
        "ID": "egerland--56604",
        "abbrkey": {},
        "book_ID": 115,
        "book_URL": "https://langsci-press.org/catalog/book/115",
        "book_metalanguage": "eng",
        "book_title": "Order and structure in syntax II",
        "categories": [
            "man"
        ],
        "citation": null,
        "clength": 64,
        "entities": [],
        "html": "<div class=\"imtblocks\">\n\t<div class=\"imtblock\">\n\t\t<div class=\"srcblock\">Man</div>\n\t\t<div class=\"glossblock\"><span class=\"sc\">man</span></div>\n\t</div>\n\t<div class=\"imtblock\">\n\t\t<div class=\"srcblock\">har</div>\n\t\t<div class=\"glossblock\">has</div>\n\t</div>\n\t<div class=\"imtblock\">\n\t\t<div class=\"srcblock\">arbetat</div>\n\t\t<div class=\"glossblock\">worked</div>\n\t</div>\n\t<div class=\"imtblock\">\n\t\t<div class=\"srcblock\">i</div>\n\t\t<div class=\"glossblock\">in</div>\n\t</div>\n\t<div class=\"imtblock\">\n\t\t<div class=\"srcblock\">två</div>\n\t\t<div class=\"glossblock\">two</div>\n\t</div>\n\t<div class=\"imtblock\">\n\t\t<div class=\"srcblock\">månader</div>\n\t\t<div class=\"glossblock\">months</div>\n\t</div>\n\t<div class=\"imtblock\">\n\t\t<div class=\"srcblock\">för</div>\n\t\t<div class=\"glossblock\">for</div>\n\t</div>\n\t<div class=\"imtblock\">\n\t\t<div class=\"srcblock\">att</div>\n\t\t<div class=\"glossblock\">to</div>\n\t</div>\n\t<div class=\"imtblock\">\n\t\t<div class=\"srcblock\">lösa</div>\n\t\t<div class=\"glossblock\">solve</div>\n\t</div>\n\t<div class=\"imtblock\">\n\t\t<div class=\"srcblock\">problemet.</div>\n\t\t<div class=\"glossblock\">problem.the</div>\n\t</div>\n</div>\n",
        "imtwordsbare": [
            "MAN",
            "has",
            "worked",
            "in",
            "two",
            "months",
            "for",
            "to",
            "solve",
            "problem.the"
        ],
        "label": "Man har arbetat i två månader för att lösa problemet.",
        "language": "https://glottolog.org/resource/languoid/id/swed1254",
        "language_glottocode": "swed1254",
        "language_iso6393": null,
        "language_name": null,
        "parententities": [],
        "srcwordsbare": [
            "Man",
            "har",
            "arbetat",
            "i",
            "två",
            "månader",
            "för",
            "att",
            "lösa",
            "problemet."
        ],
        "trs": "People/I have been working for two months to solve the problem",
        "wlength": 10
    },
    {
        "ID": "egerland-515791",
        "abbrkey": {},
        "book_ID": 115,
        "book_URL": "https://langsci-press.org/catalog/book/115",
        "book_metalanguage": "eng",
        "book_title": "Order and structure in syntax II",
        "categories": [
            "se"
        ],
        "citation": null,
        "clength": 77,
        "entities": [],
        "html": "<div class=\"imtblocks\">\n\t<div class=\"imtblock\">\n\t\t<div class=\"srcblock\">Se</div>\n\t\t<div class=\"glossblock\"><span class=\"sc\">se</span></div>\n\t</div>\n\t<div class=\"imtblock\">\n\t\t<div class=\"srcblock\">ha</div>\n\t\t<div class=\"glossblock\">has</div>\n\t</div>\n\t<div class=\"imtblock\">\n\t\t<div class=\"srcblock\">trabajado</div>\n\t\t<div class=\"glossblock\">worked</div>\n\t</div>\n\t<div class=\"imtblock\">\n\t\t<div class=\"srcblock\">durante</div>\n\t\t<div class=\"glossblock\">for</div>\n\t</div>\n\t<div class=\"imtblock\">\n\t\t<div class=\"srcblock\">dos</div>\n\t\t<div class=\"glossblock\">two</div>\n\t</div>\n\t<div class=\"imtblock\">\n\t\t<div class=\"srcblock\">meses</div>\n\t\t<div class=\"glossblock\">months</div>\n\t</div>\n\t<div class=\"imtblock\">\n\t\t<div class=\"srcblock\">para</div>\n\t\t<div class=\"glossblock\">to</div>\n\t</div>\n\t<div class=\"imtblock\">\n\t\t<div class=\"srcblock\">resolver</div>\n\t\t<div class=\"glossblock\">solve</div>\n\t</div>\n\t<div class=\"imtblock\">\n\t\t<div class=\"srcblock\">el</div>\n\t\t<div class=\"glossblock\">the</div>\n\t</div>\n\t<div class=\"imtblock\">\n\t\t<div class=\"srcblock\">problema.</div>\n\t\t<div class=\"glossblock\">problem</div>\n\t</div>\n</div>\n",
        "imtwordsbare": [
            "SE",
            "has",
            "worked",
            "for",
            "two",
            "months",
            "to",
            "solve",
            "the",
            "problem"
        ],
        "label": "Se ha trabajado durante dos meses para resolver el problema.",
        "language": null,
        "language_iso6393": null,
        "language_name": null,
        "parententities": [],
        "srcwordsbare": [
            "Se",
            "ha",
            "trabajado",
            "durante",
            "dos",
            "meses",
            "para",
            "resolver",
            "el",
            "problema."
        ],
        "trs": "people have worked for two months...",
        "wlength": 10
    },
    {
        "ID": "egerland--19861",
        "abbrkey": {},
        "book_ID": 115,
        "book_URL": "https://langsci-press.org/catalog/book/115",
        "book_metalanguage": "eng",
        "book_title": "Order and structure in syntax II",
        "categories": [
            "man"
        ],
        "citation": null,
        "clength": 71,
        "entities": [],
        "html": "<div class=\"imtblocks\">\n\t<div class=\"imtblock\">\n\t\t<div class=\"srcblock\">Man</div>\n\t\t<div class=\"glossblock\"><span class=\"sc\">man</span></div>\n\t</div>\n\t<div class=\"imtblock\">\n\t\t<div class=\"srcblock\">hat</div>\n\t\t<div class=\"glossblock\">has</div>\n\t</div>\n\t<div class=\"imtblock\">\n\t\t<div class=\"srcblock\">zwei</div>\n\t\t<div class=\"glossblock\">two</div>\n\t</div>\n\t<div class=\"imtblock\">\n\t\t<div class=\"srcblock\">Monate</div>\n\t\t<div class=\"glossblock\">months</div>\n\t</div>\n\t<div class=\"imtblock\">\n\t\t<div class=\"srcblock\">lang</div>\n\t\t<div class=\"glossblock\">long</div>\n\t</div>\n\t<div class=\"imtblock\">\n\t\t<div class=\"srcblock\">gearbeitet,</div>\n\t\t<div class=\"glossblock\">worked</div>\n\t</div>\n\t<div class=\"imtblock\">\n\t\t<div class=\"srcblock\">um</div>\n\t\t<div class=\"glossblock\">for</div>\n\t</div>\n\t<div class=\"imtblock\">\n\t\t<div class=\"srcblock\">das</div>\n\t\t<div class=\"glossblock\">the</div>\n\t</div>\n\t<div class=\"imtblock\">\n\t\t<div class=\"srcblock\">Problem</div>\n\t\t<div class=\"glossblock\">problem</div>\n\t</div>\n\t<div class=\"imtblock\">\n\t\t<div class=\"srcblock\">zu</div>\n\t\t<div class=\"glossblock\">to</div>\n\t</div>\n\t<div class=\"imtblock\">\n\t\t<div class=\"srcblock\">lösen.</div>\n\t\t<div class=\"glossblock\">solve</div>\n\t</div>\n</div>\n",
        "imtwordsbare": [
            "MAN",
            "has",
            "two",
            "months",
            "long",
            "worked",
            "for",
            "the",
            "problem",
            "to",
            "solve"
        ],
        "label": "Man hat zwei Monate lang gearbeitet, um das Problem zu lösen.",
        "language": "https://glottolog.org/resource/languoid/id/stan1295",
        "language_glottocode": "stan1295",
        "language_iso6393": null,
        "language_name": null,
        "parententities": [],
        "srcwordsbare": [
            "Man",
            "hat",
            "zwei",
            "Monate",
            "lang",
            "gearbeitet,",
            "um",
            "das",
            "Problem",
            "zu",
            "lösen."
        ],
        "trs": "(Some) people have been working for two months to solve the problem.",
        "wlength": 11
    },
    {
        "ID": "egerland-780583",
        "abbrkey": {},
        "book_ID": 115,
        "book_URL": "https://langsci-press.org/catalog/book/115",
        "book_metalanguage": "eng",
        "book_title": "Order and structure in syntax II",
        "categories": [
            "self"
        ],
        "citation": null,
        "clength": 39,
        "entities": [],
        "html": "<div class=\"imtblocks\">\n\t<div class=\"imtblock\">\n\t\t<div class=\"srcblock\">Der</div>\n\t\t<div class=\"glossblock\">the</div>\n\t</div>\n\t<div class=\"imtblock\">\n\t\t<div class=\"srcblock\">Chef</div>\n\t\t<div class=\"glossblock\">boss</div>\n\t</div>\n\t<div class=\"imtblock\">\n\t\t<div class=\"srcblock\">fährt</div>\n\t\t<div class=\"glossblock\">goes</div>\n\t</div>\n\t<div class=\"imtblock\">\n\t\t<div class=\"srcblock\">selbst</div>\n\t\t<div class=\"glossblock\"><span class=\"sc\">self</span></div>\n\t</div>\n\t<div class=\"imtblock\">\n\t\t<div class=\"srcblock\">in</div>\n\t\t<div class=\"glossblock\">on</div>\n\t</div>\n\t<div class=\"imtblock\">\n\t\t<div class=\"srcblock\">Urlaub.</div>\n\t\t<div class=\"glossblock\">holiday</div>\n\t</div>\n</div>\n",
        "imtwordsbare": [
            "the",
            "boss",
            "goes",
            "SELF",
            "on",
            "holiday"
        ],
        "label": "Der Chef fährt selbst in Urlaub.",
        "language": "https://glottolog.org/resource/languoid/id/stan1295",
        "language_glottocode": "stan1295",
        "language_iso6393": null,
        "language_name": null,
        "parententities": [],
        "srcwordsbare": [
            "Der",
            "Chef",
            "fährt",
            "selbst",
            "in",
            "Urlaub."
        ],
        "trs": "...the boss himself / even the boss / the boss too is going on a holiday.",
        "wlength": 6
    },
    {
        "ID": "egerland--83828",
        "abbrkey": {},
        "book_ID": 115,
        "book_URL": "https://langsci-press.org/catalog/book/115",
        "book_metalanguage": "eng",
        "book_title": "Order and structure in syntax II",
        "categories": [
            "self"
        ],
        "citation": null,
        "clength": 37,
        "entities": [],
        "html": "<div class=\"imtblocks\">\n\t<div class=\"imtblock\">\n\t\t<div class=\"srcblock\">Selbst</div>\n\t\t<div class=\"glossblock\"><span class=\"sc\">self</span></div>\n\t</div>\n\t<div class=\"imtblock\">\n\t\t<div class=\"srcblock\">fährt</div>\n\t\t<div class=\"glossblock\">goes</div>\n\t</div>\n\t<div class=\"imtblock\">\n\t\t<div class=\"srcblock\">der</div>\n\t\t<div class=\"glossblock\">the</div>\n\t</div>\n\t<div class=\"imtblock\">\n\t\t<div class=\"srcblock\">Chef</div>\n\t\t<div class=\"glossblock\">boss</div>\n\t</div>\n\t<div class=\"imtblock\">\n\t\t<div class=\"srcblock\">in</div>\n\t\t<div class=\"glossblock\">on</div>\n\t</div>\n\t<div class=\"imtblock\">\n\t\t<div class=\"srcblock\">Urlaub.</div>\n\t\t<div class=\"glossblock\">holiday</div>\n\t</div>\n</div>\n",
        "imtwordsbare": [
            "SELF",
            "goes",
            "the",
            "boss",
            "on",
            "holiday"
        ],
        "label": "Selbst fährt der Chef in Urlaub.",
        "language": "https://glottolog.org/resource/languoid/id/stan1295",
        "language_glottocode": "stan1295",
        "language_iso6393": null,
        "language_name": null,
        "parententities": [],
        "srcwordsbare": [
            "Selbst",
            "fährt",
            "der",
            "Chef",
            "in",
            "Urlaub."
        ],
        "trs": "... but the boss, on the other hand, is leaving for a holiday.",
        "wlength": 6
    },
    {
        "ID": "egerland--22959",
        "abbrkey": {},
        "book_ID": 115,
        "book_URL": "https://langsci-press.org/catalog/book/115",
        "book_metalanguage": "eng",
        "book_title": "Order and structure in syntax II",
        "categories": [],
        "citation": null,
        "clength": 51,
        "entities": [],
        "html": "<div class=\"imtblocks\">\n\t<div class=\"imtblock\">\n\t\t<div class=\"srcblock\">Eg</div>\n\t\t<div class=\"glossblock\">I</div>\n\t</div>\n\t<div class=\"imtblock\">\n\t\t<div class=\"srcblock\">vona</div>\n\t\t<div class=\"glossblock\">hope</div>\n\t</div>\n\t<div class=\"imtblock\">\n\t\t<div class=\"srcblock\">að</div>\n\t\t<div class=\"glossblock\">that</div>\n\t</div>\n\t<div class=\"imtblock\">\n\t\t<div class=\"srcblock\">maður</div>\n\t\t<div class=\"glossblock\"><span class=\"sc\">maður</span></div>\n\t</div>\n\t<div class=\"imtblock\">\n\t\t<div class=\"srcblock\">verði</div>\n\t\t<div class=\"glossblock\">will.be</div>\n\t</div>\n\t<div class=\"imtblock\">\n\t\t<div class=\"srcblock\">ekki</div>\n\t\t<div class=\"glossblock\">not</div>\n\t</div>\n\t<div class=\"imtblock\">\n\t\t<div class=\"srcblock\">of</div>\n\t\t<div class=\"glossblock\">too</div>\n\t</div>\n\t<div class=\"imtblock\">\n\t\t<div class=\"srcblock\">seinn.</div>\n\t\t<div class=\"glossblock\">late</div>\n\t</div>\n</div>\n",
        "imtwordsbare": [
            "I",
            "hope",
            "that",
            "maður",
            "will.be",
            "not",
            "too",
            "late"
        ],
        "label": "Eg vona að maður verði ekki of seinn.",
        "language": "https://glottolog.org/resource/languoid/id/icel1247",
        "language_glottocode": "icel1247",
        "language_iso6393": null,
        "language_name": null,
        "parententities": [],
        "srcwordsbare": [
            "Eg",
            "vona",
            "að",
            "maður",
            "verði",
            "ekki",
            "of",
            "seinn."
        ],
        "trs": "I hope I won’t be late.",
        "wlength": 8
    },
    {
        "ID": "egerland--39022",
        "abbrkey": {},
        "book_ID": 115,
        "book_URL": "https://langsci-press.org/catalog/book/115",
        "book_metalanguage": "eng",
        "book_title": "Order and structure in syntax II",
        "categories": [
            "man",
            "self"
        ],
        "citation": null,
        "clength": 45,
        "entities": [],
        "html": "<div class=\"imtblocks\">\n\t<div class=\"imtblock\">\n\t\t<div class=\"srcblock\">Maður</div>\n\t\t<div class=\"glossblock\"><span class=\"sc\">man</span></div>\n\t</div>\n\t<div class=\"imtblock\">\n\t\t<div class=\"srcblock\">verður</div>\n\t\t<div class=\"glossblock\">must</div>\n\t</div>\n\t<div class=\"imtblock\">\n\t\t<div class=\"srcblock\">sjálfur</div>\n\t\t<div class=\"glossblock\"><span class=\"sc\">self</span></div>\n\t</div>\n\t<div class=\"imtblock\">\n\t\t<div class=\"srcblock\">að</div>\n\t\t<div class=\"glossblock\">to</div>\n\t</div>\n\t<div class=\"imtblock\">\n\t\t<div class=\"srcblock\">þrífa</div>\n\t\t<div class=\"glossblock\">clean</div>\n\t</div>\n\t<div class=\"imtblock\">\n\t\t<div class=\"srcblock\">herbergið.</div>\n\t\t<div class=\"glossblock\">room.the</div>\n\t</div>\n</div>\n",
        "imtwordsbare": [
            "MAN",
            "must",
            "SELF",
            "to",
            "clean",
            "room.the"
        ],
        "label": "Maður verður sjálfur að þrífa herbergið.",
        "language": "https://glottolog.org/resource/languoid/id/icel1247",
        "language_glottocode": "icel1247",
        "language_iso6393": null,
        "language_name": null,
        "parententities": [],
        "srcwordsbare": [
            "Maður",
            "verður",
            "sjálfur",
            "að",
            "þrífa",
            "herbergið."
        ],
        "trs": "a. ‘People have to clean their rooms themselves / on their own.",
        "wlength": 6
    },
    {
        "ID": "egerland-190214",
        "abbrkey": {},
        "book_ID": 115,
        "book_URL": "https://langsci-press.org/catalog/book/115",
        "book_metalanguage": "eng",
        "book_title": "Order and structure in syntax II",
        "categories": [
            "man",
            "self"
        ],
        "citation": null,
        "clength": 44,
        "entities": [],
        "html": "<div class=\"imtblocks\">\n\t<div class=\"imtblock\">\n\t\t<div class=\"srcblock\">Man</div>\n\t\t<div class=\"glossblock\"><span class=\"sc\">man</span></div>\n\t</div>\n\t<div class=\"imtblock\">\n\t\t<div class=\"srcblock\">muss</div>\n\t\t<div class=\"glossblock\">must</div>\n\t</div>\n\t<div class=\"imtblock\">\n\t\t<div class=\"srcblock\">das</div>\n\t\t<div class=\"glossblock\">the</div>\n\t</div>\n\t<div class=\"imtblock\">\n\t\t<div class=\"srcblock\">Zimmer</div>\n\t\t<div class=\"glossblock\">room</div>\n\t</div>\n\t<div class=\"imtblock\">\n\t\t<div class=\"srcblock\">selbst</div>\n\t\t<div class=\"glossblock\"><span class=\"sc\">self</span></div>\n\t</div>\n\t<div class=\"imtblock\">\n\t\t<div class=\"srcblock\">aufräumen.</div>\n\t\t<div class=\"glossblock\">clean</div>\n\t</div>\n</div>\n",
        "imtwordsbare": [
            "MAN",
            "must",
            "the",
            "room",
            "SELF",
            "clean"
        ],
        "label": "Man muss das Zimmer selbst aufräumen.",
        "language": "https://glottolog.org/resource/languoid/id/stan1295",
        "language_glottocode": "stan1295",
        "language_iso6393": null,
        "language_name": null,
        "parententities": [],
        "srcwordsbare": [
            "Man",
            "muss",
            "das",
            "Zimmer",
            "selbst",
            "aufräumen."
        ],
        "trs": "People have to clean their rooms themselves.",
        "wlength": 6
    },
    {
        "ID": "egerland--43233",
        "abbrkey": {},
        "book_ID": 115,
        "book_URL": "https://langsci-press.org/catalog/book/115",
        "book_metalanguage": "eng",
        "book_title": "Order and structure in syntax II",
        "categories": [
            "man",
            "self"
        ],
        "citation": null,
        "clength": 45,
        "coordination": "and",
        "entities": [],
        "html": "<div class=\"imtblocks\">\n\t<div class=\"imtblock\">\n\t\t<div class=\"srcblock\">sjálfur</div>\n\t\t<div class=\"glossblock\"><span class=\"sc\">self</span></div>\n\t</div>\n\t<div class=\"imtblock\">\n\t\t<div class=\"srcblock\">verður</div>\n\t\t<div class=\"glossblock\">must</div>\n\t</div>\n\t<div class=\"imtblock\">\n\t\t<div class=\"srcblock\">maður</div>\n\t\t<div class=\"glossblock\"><span class=\"sc\">man</span></div>\n\t</div>\n\t<div class=\"imtblock\">\n\t\t<div class=\"srcblock\">að</div>\n\t\t<div class=\"glossblock\">to</div>\n\t</div>\n\t<div class=\"imtblock\">\n\t\t<div class=\"srcblock\">þrífa</div>\n\t\t<div class=\"glossblock\">clean</div>\n\t</div>\n\t<div class=\"imtblock\">\n\t\t<div class=\"srcblock\">herbergið.</div>\n\t\t<div class=\"glossblock\">room.the</div>\n\t</div>\n</div>\n",
        "imtwordsbare": [
            "SELF",
            "must",
            "MAN",
            "to",
            "clean",
            "room.the"
        ],
        "label": "sjálfur verður maður að þrífa herbergið.",
        "language": "https://glottolog.org/resource/languoid/id/icel1247",
        "language_glottocode": "icel1247",
        "language_iso6393": null,
        "language_name": null,
        "parententities": [],
        "srcwordsbare": [
            "sjálfur",
            "verður",
            "maður",
            "að",
            "þrífa",
            "herbergið."
        ],
        "trs": "… but I have to stay at home and clean my room.",
        "wlength": 6
    }
]